Workbook

Sheet RAW_Forecast_Data
A1: Rep_ID | B1: Rep_Name | C1: Segment | D1: Week_Ending_Date | E1: Quarter | F1: Forecasted_Revenue | G1: Actual_Revenue_Closed | H1: Pipeline_Value | I1: Weighted_Pipeline | J1: Stage_Distribution | K1: Deal_Count_Forecasted | L1: Deal_Count_Closed | M1: Forecast_Submitted_On_Time | N1: Notes
A2: E01 | B2: James Whitfield | C2: Enterprise | D2: 05/01/2024 | E2: Q1 2024 | F2: 83501.51 | G2: 80495.84 | H2: 237882.83 | I2: 72771.57 | J2: Qualify:20%,Propose:20%,Negotiate:40%,Close:20% | K2: 5 | L2: 4 | M2: Y
A3: E02 | B3: Sarah Thornton | C3: Enterprise | D3: 2024-01-05 | E3: Jan-Mar 2024 | F3: 101890.04 | G3: 187730.93 | H3: 432558.75 | I3: 89293.76 | J3: Qualify:10%,Propose:35%,Negotiate:40%,Close:15% | K3: 3 | L3: 3 | M3: Y | N3: Verbal commit received – awaiting paperwork
A4: E03 | B4: Marcus Bellingham | C4: enterprise | D4: 05/01/2024 | E4: Q1 2024 | F4: 196116.65 | G4: 199835.64 | H4: 773362.56 | I4: 145229.87 | J4: Qualify:20%,Propose:20%,Negotiate:40%,Close:20% | K4: 2 | L4: 6 | M4: Yes | N4: Budget freeze reported by prospect
A5: E04 | B5: Olivia Hargreaves | C5: Enterprise | D5: 05-01-2024 | E5: Q1 2024 | F5: 175696.67 | G5: 163648.17 | H5: 673858.18 | I5: 174249.1 | J5: Qualify:25%,Propose:30%,Negotiate:35%,Close:10% | K5: 3 | L5: 3 | M5: Late | N5: NA
A6: E05 | B6: Richard Cavendish | C6: enterprise | D6: 05-01-2024 | E6: Jan-Mar 2024 | F6: 109537.6 | G6: 117300.04 | H6: 332070.5 | I6: 109714.81 | J6: Qualify:15%,Propose:40%,Negotiate:25%,Close:20% | K6: 6 | L6: 6 | M6: YES | N6: Revised following manager review
A7: E06 | B7: Helena Forsythe | C7: ENTERPRISE | D7: 05.01.2024 | E7: Q1 2024 | F7: 92727.32 | G7: 86008.17 | H7: £267,249 | I7: 79020.88 | J7: Qualify:20%,Propose:20%,Negotiate:40%,Close:20% | K7: 5 | L7: 2 | M7: Y
A8: M01 | B8: Daniel Ashworth | C8: Mid-Market | D8: 05/01/24 | E8: Jan-Mar 2024 | F8: 58658.74 | G8: 93144.86 | H8: 286520.93 | I8: 64403.07 | J8: Qualify:5%,Propose:45%,Negotiate:30%,Close:20% | K8: 5 | L8: 1 | M8: y
A9: M02 | B9: Priya Mehta | C9: MM | D9: 05/01/2024 | E9: Q1 2024 | F9: 65936.68 | G9: 65711.28 | H9: 317995.87 | I9: 102198.51 | J9: Qualify:15%,Propose:40%,Negotiate:25%,Close:20% | K9: 3 | L9: 2 | M9: yes
A10: M03 | B10: Tom Baxter | C10: MidMarket | D10: 05/01/2024 | E10: Q1 2024 | F10: 543030 | G10: 30943.06 | H10: 2325305 | I10: 68408.93 | J10: Qualify:15%,Propose:40%,Negotiate:25%,Close:20% | K10: 3 | L10: 4 | M10: y | N10: Verbal commit received – awaiting paperwork
A11: M04 | B11: Claire Pemberton | C11: MM | D11: 05.01.2024 | E11: Q1 2024 | F11: 81578.12 | G11: 71075.53 | H11: 260739.44 | I11: 70835.02 | J11: Qualify:25%,Propose:30%,Negotiate:35%,Close:10% | K11: 6 | L11: 4 | M11: n | N11: -
A12: M05 | B12: Nathan Griffiths | C12: MM | D12: 05.01.2024 | E12: Q1 2024 | F12: 81830.2 | G12: 70885.53 | H12: 216975.38 | I12: 68586.08 | J12: Qualify:5%,Propose:45%,Negotiate:30%,Close:20% | K12: 1 | L12: 2 | M12: yes
A13: M06 | B13: Yasmin Khalid | C13: mid-market | D13: 05 Jan 2024 | E13: Q1-2024 | F13: 69128.69 | G13: 69970.43 | H13: 340285.35 | I13: 110347.15 | J13: Qualify:10%,Propose:35%,Negotiate:40%,Close:15% | K13: 2 | L13: 1 | M13: Y | N13: Forecast includes upsell opportunity
A14: M07 | B14: Andrew Collinson | C14: Mid market | D14: 2024-01-05 | E14: Q1 2024 | F14: 87439.06 | G14: 100434.85 | H14: 252435.87 | I14: 87009.74 | J14: Qualify:30%,Propose:25%,Negotiate:25%,Close:20% | K14: 5 | L14: 8 | M14: Yes | N14: Verbal commit received – awaiting paperwork
A15: S01 | B15: Lucy Drummond | C15: SMB | D15: 05/01/2024 | E15: Q1 2024 | F15: 9850.08 | G15: 7722.27 | H15: 30417.13 | I15: 10078.68 | J15: Qualify:20%,Propose:20%,Negotiate:40%,Close:20% | K15: 5 | L15: 15 | M15: Yes | N15: n/a
A16: S02 | B16: Ben Hartley | C16: SMB | D16: 05/01/24 | E16: Q1 2024 | F16: 24852.66 | G16: 12914.1 | H16: 4330.13 | I16: 1193.85 | J16: Qualify:10%,Propose:35%,Negotiate:40%,Close:15% | K16: 3 | L16: 14 | M16: yes
A17: S03 | B17: Fiona McKenzie | C17: Smb | D17: 05/01/2024 | E17: Jan-Mar 2024 | F17: 24515.3 | G17: 30487.63 | H17: 93706.1 | I17: 25701.93 | J17: Qualify:20%,Propose:20%,Negotiate:40%,Close:20% | K17: 12 | L17: 12 | M17: yes | N17: Budget freeze reported by prospect
A18: S04 | B18: Callum Reid | C18: S M B | D18: 05/01/24 | E18: Q1 2024 | F18: 14780.27 | G18: 17796.63 | H18: 40361.18 | I18: 9163.43 | J18: Qualify:20%,Propose:20%,Negotiate:40%,Close:20% | K18: 2 | L18: 2 | M18: yes | N18: Revised following manager review
A19: S05 | B19: Amara Osei | C19: S M B | D19: 05-01-2024 | E19: Q1 2024 | F19: 30534.07 | G19: 31793.74 | H19: 3753.56 | I19: 1271.05 | J19: Qualify:20%,Propose:20%,Negotiate:40%,Close:20% | K19: 2 | L19: 4 | M19: no | N19: Revised following manager review
A20: S06 | B20: Steven Bowman | C20: Smb | D20: 05/01/2024 | E20: Q1 2024 | F20: 19860.67 | G20: 9686 | H20: 50882.36 | I20: 12032.23 | J20: Qualify:10%,Propose:35%,Negotiate:40%,Close:15% | K20: 8 | L20: 8 | M20: yes | N20: N/A
A21: S07 | B21: Rachel Sutton | C21: Smb | D21: 05 Jan 2024 | E21: Q1 2024 | F21: 29474.33 | G21: 25459.86 | H21: 122320k | I21: 27811.19 | J21: Qualify:15%,Propose:40%,Negotiate:25%,Close:20% | K21: 3 | L21: 2 | M21: NO
A22: E01 | B22: James Whitfield | C22: enterprise | D22: 12/01/24 | E22: Q1 2024 | F22: 117165.29 | G22: 109824.23 | H22: 394169.55 | I22: 100192.76 | J22: Qualify:20%,Propose:20%,Negotiate:40%,Close:20% | K22: 5 | L22: 7 | M22: y | N22: New logo opportunity added
A23: E02 | B23: Sarah Thornton | C23: ENTERPRISE | D23: 12/01/2024 | E23: Q1 2024 | F23: 68871.99 | G23: 111983.87 | H23: 296107.25 | I23: 68868.15 | J23: Qualify:30%,Propose:25%,Negotiate:25%,Close:20% | K23: 4 | L23: 2 | M23: YES | N23: Forecast includes upsell opportunity
A24: E03 | B24: Marcus Bellingham | C24: ENTERPRISE | D24: 12.01.2024 | E24: Q1-2024 | F24: 196721.52 | G24: 190548.4 | H24: 703224.44 | I24: 204849.25 | J24: Qualify:20%,Propose:35%,Negotiate:30%,Close:15% | K24: 4 | L24: 4 | M24: yes | N24: Deal pulled forward from next quarter
A25: E04 | B25: Olivia Hargreaves | C25: enterprise | D25: 12 Jan 2024 | E25: Q1 2024 | F25: 111449.69 | G25: 106084.59 | H25: £291,500 | I25: 82761.82 | J25: Qualify:5%,Propose:45%,Negotiate:30%,Close:20% | K25: 1 | L25: 1 | M25: y | N25: -
A26: E05 | B26: Richard Cavendish | C26: Enterprise | D26: 2024-01-12 | E26: q1 2024 | F26: 192575.38 | G26: 198611.83 | H26: 505615.51 | I26: 163929.23 | J26: Qualify:30%,Propose:25%,Negotiate:25%,Close:20% | K26: 4 | L26: 8 | M26: Y | N26: none
A27: E06 | B27: Helena Forsythe | C27: ENT | D27: 12.01.2024 | E27: Q1 2024 | F27: 184111.76 | G27: 183365.72 | H27: 806306.78 | I27: 183146.88 | J27: Qualify:15%,Propose:40%,Negotiate:25%,Close:20% | K27: 5 | L27: 5 | M27: yes | N27: Revised following manager review
A28: M01 | B28: Daniel Ashworth | C28: MM | D28: 12 Jan 2024 | E28: Q1 2024 | F28: 56849.47 | G28: 90344.27 | H28: 201215.05 | I28: 50590.37 | J28: Qualify:5%,Propose:45%,Negotiate:30%,Close:20% | K28: 5 | L28: 8 | M28: No | N28: -
A29: M02 | B29: Priya Mehta | C29: Mid market | D29: 12/01/2024 | E29: Q1-2024 | F29: 74078.04 | G29: 80742.14 | H29: 275612.82 | I29: 72364.66 | J29: Qualify:20%,Propose:20%,Negotiate:40%,Close:20% | K29: 4 | L29: 4 | M29: Y | N29: Pipeline updated post-QBR
A30: M03 | B30: Tom Baxter | C30: Mid Market | D30: 12/01/2024 | E30: Q1 2024 | F30: 73444.33 | G30: 38100.26 | H30: 222473.95 | I30: 68835.45 | J30: Qualify:20%,Propose:35%,Negotiate:30%,Close:15% | K30: 4 | L30: 6 | M30: Y | N30: Two deals slipped to next week
A31: M04 | B31: Claire Pemberton | C31: MidMarket | D31: 12/01/24 | E31: Q1-2024 | F31: 86976.7 | G31: 79132.12 | H31: 352546.08 | I31: 91840.15 | J31: Qualify:15%,Propose:40%,Negotiate:25%,Close:20% | K31: 1 | L31: 1 | M31: yes | N31: Forecast includes upsell opportunity
A32: M07 | B32: Andrew Collinson | C32: Mid market | D32: 12/01/2024 | E32: Jan-Mar 2024 | F32: 70640.84 | G32: 80350.55 | H32: 342867.77 | I32: 96228.12 | J32: Qualify:30%,Propose:25%,Negotiate:25%,Close:20% | K32: 6 | L32: 7 | M32: YES | N32: n/a
A33: S02 | B33: Ben Hartley | C33: Small Business | D33: 12.01.2024 | E33: Q1 2024 | F33: 28375.2 | G33: 16264.33 | H33: 121113.07 | I33: 36908.63 | J33: Qualify:20%,Propose:35%,Negotiate:30%,Close:15% | K33: 12 | L33: 9 | M33: y | N33: Budget freeze reported by prospect
A34: S03 | B34: Fiona McKenzie | C34: Smb | D34: 12/01/24 | E34: Q1 2024 | F34: 14584.31 | G34: 14326.96 | H34: 610823 | I34: 16059.35 | J34: Qualify:15%,Propose:40%,Negotiate:25%,Close:20% | K34: 7 | L34: 11 | M34: yes | N34: -
A35: S04 | B35: Callum Reid | C35: Smb | D35: 2024-01-12 | E35: Q1 2024 | F35: 28470.45 | G35: 31183.81 | H35: 121842.29 | I35: 22288.78 | J35: Qualify:20%,Propose:20%,Negotiate:40%,Close:20% | K35: 6 | L35: 12 | M35: yes | N35: none
A36: S05 | B36: Amara Osei | C36: Smb | D36: 12/01/24 | E36: Q1-2024 | F36: 14787.9 | G36: 11983.05 | H36: 48635.48 | I36: 16616.27 | J36: Qualify:15%,Propose:40%,Negotiate:25%,Close:20% | K36: 4 | L36: 5 | M36: Y | N36: Budget freeze reported by prospect
A37: S07 | B37: Rachel Sutton | C37: Small Business | D37: 2024-01-12 | E37: Q1 2024 | F37: 15887.69 | G37: 19415.47 | H37: 74213.83 | I37: 24369.03 | J37: Qualify:10%,Propose:35%,Negotiate:40%,Close:15% | K37: 11 | L37: 12 | M37: Y
A38: E01 | B38: James Whitfield | C38: ENTERPRISE | D38: 19-01-2024 | E38: q1 2024 | F38: 168122.4 | G38: 156114.67 | H38: 761233.88 | I38: 148045.34 | J38: Qualify:25%,Propose:30%,Negotiate:35%,Close:10% | K38: 2 | L38: 3 | M38: Y
A39: E02 | B39: Sarah Thornton | C39: Ent | D39: 19.01.2024 | E39: Q1 2024 | F39: 116610.42 | G39: 203571.6 | H39: 368677.28 | I39: 81395.49 | J39: Qualify:5%,Propose:45%,Negotiate:30%,Close:20% | K39: 5 | L39: 4 | M39: Yes | N39: none
A40: E03 | B40: Marcus Bellingham | C40: Enterprise | D40: 19/01/2024 | E40: Jan-Mar 2024 | F40: 112679.33 | G40: 108434.56 | H40: 401459.27 | I40: 116462.49 | J40: Qualify:20%,Propose:20%,Negotiate:40%,Close:20% | K40: 3 | L40: 4 | M40: Yes | N40: Forecast includes upsell opportunity
A41: E04 | B41: Olivia Hargreaves | C41: Enterprise | D41: 19/01/2024 | E41: Q1 2024 | F41: 211974.67 | G41: 211990.69 | H41: 7619241 | I41: 252349.73 | J41: Qualify:30%,Propose:25%,Negotiate:25%,Close:20% | K41: 6 | L41: 8 | M41: YES | N41: Two deals slipped to next week
A42: E05 | B42: Richard Cavendish | C42: Ent | D42: 2024-01-19 | E42: Q1 2024 | F42: 104526.7 | G42: 104843.86 | H42: 500701.92 | I42: 139949.21 | J42: Qualify:10%,Propose:35%,Negotiate:40%,Close:15% | K42: 6 | L42: 8 | M42: Yes | N42: Forecast includes upsell opportunity
A43: E06 | B43: Helena Forsythe | C43: Enterprise | D43: 19.01.2024 | E43: Q1 2024 | F43: 136063.32 | G43: 141734.43 | H43: 494871.09 | I43: 116273.2 | J43: Qualify:5%,Propose:45%,Negotiate:30%,Close:20% | K43: 4 | L43: 1 | M43: Yes | N43: Two deals slipped to next week
A44: M01 | B44: Daniel Ashworth | C44: Mid-Market | D44: 19 Jan 2024 | E44: Q1 2024 | F44: 47604.46 | G44: 82137.37 | H44: 122446.94 | I44: 38678.95 | J44: Qualify:5%,Propose:45%,Negotiate:30%,Close:20% | K44: 6 | L44: 2 | M44: y | N44: Revised following manager review
A45: M02 | B45: Priya Mehta | C45: mid-market | D45: 19/01/2024 | E45: Q1 | F45: 72996.2 | G45: 73190.49 | H45: 258313.54 | I45: 67233.17 | J45: Qualify:25%,Propose:30%,Negotiate:35%,Close:10% | K45: 4 | L45: 5 | M45: Y | N45: Pipeline updated post-QBR
A46: M03 | B46: Tom Baxter | C46: mid-market | D46: 19-01-2024 | E46: Q1 2024 | F46: 67073.43 | G46: 34193.52 | H46: GBP 242,562 | I46: 57369.56 | J46: Qualify:20%,Propose:20%,Negotiate:40%,Close:20% | K46: 5 | L46: 3 | M46: YES | N46: NA
A47: M04 | B47: Claire Pemberton | C47: Mid-Market | D47: 19.01.2024 | E47: Q1 2024 | F47: 69821.33 | G47: 76539.84 | H47: 10505.19 | I47: 2944.93 | J47: Qualify:5%,Propose:45%,Negotiate:30%,Close:20% | K47: 1 | L47: 3 | M47: Y | N47: Budget freeze reported by prospect
A48: M05 | B48: Nathan Griffiths | C48: MM | D48: 19/01/2024 | E48: Q1 2024 | F48: 71562.28 | G48: 74779.07 | H48: 331394.4 | I48: 81059.6 | J48: Qualify:20%,Propose:35%,Negotiate:30%,Close:15% | K48: 3 | L48: 6 | M48: Y | N48: -
A49: M06 | B49: Yasmin Khalid | C49: Mid Market | D49: 2024-01-19 | E49: Q1 2024 | F49: 75622.18 | G49: 80247.78 | H49: 272935.3 | I49: 91046.33 | J49: Qualify:15%,Propose:40%,Negotiate:25%,Close:20% | K49: 1 | L49: 2 | M49: Yes | N49: Large renewal included
A50: M07 | B50: Andrew Collinson | C50: Mid market | D50: 19/01/2024 | E50: q1 2024 | F50: 82250.38 | G50: 85204.24 | H50: 307959.24 | I50: 67588.44 | J50: Qualify:25%,Propose:30%,Negotiate:35%,Close:10% | K50: 6 | L50: 4 | M50: YES
A51: S01 | B51: Lucy Drummond | C51: SMB | D51: 2024-01-19 | E51: Q1 2024 | F51: 33974.78 | G51: 37207.72 | H51: 156734.51 | I51: 38462.31 | J51: Qualify:25%,Propose:30%,Negotiate:35%,Close:10% | K51: 9 | L51: 9 | M51: Y | N51: Pipeline updated post-QBR
A52: S02 | B52: Ben Hartley | C52: smb | D52: 19-01-2024 | E52: Q1 2024 | F52: 34601.61 | G52: 19326.16 | H52: 158547.95 | I52: 49447.29 | J52: Qualify:20%,Propose:20%,Negotiate:40%,Close:20% | K52: 5 | L52: 9 | M52: YES | N52: Customer procurement delay
A53: S03 | B53: Fiona McKenzie | C53: smb | D53: 19-01-2024 | E53: Q1 2024 | F53: 25451.2 | G53: 23019.75 | H53: 65750.91 | I53: 13304.04 | J53: Qualify:5%,Propose:45%,Negotiate:30%,Close:20% | K53: 6 | L53: 9 | M53: Y | N53: Large renewal included
A54: S04 | B54: Callum Reid | C54: smb | D54: 19 Jan 2024 | E54: Jan-Mar 2024 | F54: 30266.62 | G54: 29991.92 | H54: £97,998 | I54: 31038.17 | J54: Qualify:10%,Propose:35%,Negotiate:40%,Close:15% | K54: 9 | L54: 14 | M54: no | N54: N/A
A55: S05 | B55: Amara Osei | C55: Smb | D55: 19-01-2024 | E55: Q1 2024 | F55: 26153.2 | G55: 27258.96 | H55: 107133.27 | I55: 31574.56 | J55: Qualify:20%,Propose:35%,Negotiate:30%,Close:15% | K55: 9 | L55: 15 | M55: y | N55: Revised following manager review
A56: E01 | B56: James Whitfield | C56: ENTERPRISE | D56: 26/01/2024 | E56: Q1 2024 | F56: 96256.87 | G56: 92172.5 | H56: 334166.74 | I56: 114082.77 | J56: Qualify:20%,Propose:20%,Negotiate:40%,Close:20% | K56: 6 | L56: 3 | M56: N | N56: N/A
A57: E02 | B57: Sarah Thornton | C57: Ent | D57: 26/01/2024 | E57: Q1 2024 | F57: 108646.46 | G57: 191640.54 | H57: 419501k | I57: 101089.27 | J57: Qualify:15%,Propose:40%,Negotiate:25%,Close:20% | K57: 4 | L57: 6 | M57: Yes | N57: Revised following manager review
A58: E03 | B58: Marcus Bellingham | C58: Enterprise | D58: 26/01/24 | E58: Q1-2024 | F58: 108728.78 | G58: 114466.49 | H58: 431213.75 | I58: 94698.75 | J58: Qualify:5%,Propose:45%,Negotiate:30%,Close:20% | K58: 2 | L58: 4 | M58: y | N58: Pipeline updated post-QBR
A59: E04 | B59: Olivia Hargreaves | C59: Ent | D59: 26.01.2024 | E59: Jan-Mar 2024 | F59: 130153.92 | G59: 136160.4 | H59: 330519.72 | I59: 66615.9 | J59: Qualify:20%,Propose:20%,Negotiate:40%,Close:20% | K59: 4 | L59: 6 | M59: Yes
A60: E05 | B60: Richard Cavendish | C60: Enterprise | D60: 2024-01-26 | E60: Q1 2024 | F60: 170067.7 | G60: 157309.91 | H60: 785414.52 | I60: 155789.73 | J60: Qualify:25%,Propose:30%,Negotiate:35%,Close:10% | K60: 6 | L60: 8 | M60: No | N60: NA
A61: E06 | B61: Helena Forsythe | C61: Enterprise | D61: 26-01-2024 | E61: Q1 2024 | F61: 154277.96 | G61: 153135.45 | H61: 423947.52 | I61: 137772.25 | J61: Qualify:20%,Propose:20%,Negotiate:40%,Close:20% | K61: 6 | L61: 7 | M61: y | N61: Customer procurement delay
A62: M01 | B62: Daniel Ashworth | C62: mid-market | D62: 26/01/2024 | E62: Q1 2024 | F62: 34352.23 | G62: 63524.22 | H62: 91646.03 | I62: 17948.79 | J62: Qualify:20%,Propose:20%,Negotiate:40%,Close:20% | K62: 1 | L62: 8 | M62: YES | N62: -
A63: M02 | B63: Priya Mehta | C63: Mid Market | D63: 2024-01-26 | E63: Q1 2024 | F63: 73263.64 | G63: 83558.62 | H63: 247566.3 | I63: 53515.32 | J63: Qualify:5%,Propose:45%,Negotiate:30%,Close:20% | K63: 6 | L63: 5 | M63: Yes
A64: M03 | B64: Tom Baxter | C64: mid-market | D64: 26 Jan 2024 | E64: Q1 2024 | F64: 95500.52 | G64: 51958.3 | H64: 245663.9 | I64: 76059.91 | J64: Qualify:10%,Propose:35%,Negotiate:40%,Close:15% | K64: 3 | L64: 5 | M64: yes | N64: -
A65: M04 | B65: Claire Pemberton | C65: Mid-Market | D65: 26/01/2024 | E65: Q1 2024 | F65: 39444.56 | G65: 37215.59 | H65: 175216.23 | I65: 34069.52 | J65: Qualify:5%,Propose:45%,Negotiate:30%,Close:20% | K65: 1 | L65: 6 | M65: y
A66: M06 | B66: Yasmin Khalid | C66: Mid Market | D66: 26-01-2024 | E66: Q1 | F66: 46994.79 | G66: 49511.17 | H66: 179394.86 | I66: 39016.25 | J66: Qualify:15%,Propose:40%,Negotiate:25%,Close:20% | K66: 5 | L66: 8 | M66: yes | N66: NA
A67: M07 | B67: Andrew Collinson | C67: Mid Market | D67: 26 Jan 2024 | E67: Q1 2024 | F67: 43806.64 | G67: 44578.39 | H67: 1127410 | I67: 21978.15 | J67: Qualify:5%,Propose:45%,Negotiate:30%,Close:20% | K67: 1 | L67: 6 | M67: Yes
A68: S01 | B68: Lucy Drummond | C68: S M B | D68: 2024-01-26 | E68: Q1 2024 | F68: 26619.47 | G68: 24780.77 | H68: 122748 | I68: 34382.71 | J68: Qualify:15%,Propose:40%,Negotiate:25%,Close:20% | K68: 10 | L68: 8 | M68: YES | N68: N/A
A69: S02 | B69: Ben Hartley | C69: Small Business | D69: 26.01.2024 | E69: Q1 2024 | F69: 44533.9 | G69: 22469.51 | H69: 133297.94 | I69: 41220.6 | J69: Qualify:20%,Propose:20%,Negotiate:40%,Close:20% | K69: 12 | L69: 6 | M69: Y | N69: n/a
A70: S03 | B70: Fiona McKenzie | C70: SMB | D70: 26/01/2024 | E70: Q1 2024 | F70: 9843.73 | G70: 9559.28 | H70: 44206.46 | I70: 10602.04 | J70: Qualify:30%,Propose:25%,Negotiate:25%,Close:20% | K70: 3 | L70: 6 | M70: Y
A71: S04 | B71: Callum Reid | C71: Small Business | D71: 26/01/2024 | E71: q1 2024 | F71: 23668.89 | G71: 29044.47 | H71: 112183.27 | I71: 35637.11 | J71: Qualify:30%,Propose:25%,Negotiate:25%,Close:20% | K71: 12 | L71: 13 | M71: y | N71: Large renewal included
A72: S06 | B72: Steven Bowman | C72: SMB | D72: 2024-01-26 | E72: Q1 2024 | F72: 47303.09 | G72: 24236.03 | H72: 164072.72 | I72: 48469.15 | J72: Qualify:30%,Propose:25%,Negotiate:25%,Close:20% | K72: 2 | L72: 6 | M72: YES | N72: Revised following manager review
A73: S07 | B73: Rachel Sutton | C73: Smb | D73: 26 Jan 2024 | E73: Q1 2024 | F73: 23733.97 | G73: 19478.8 | H73: 77742.49 | I73: 22744.57 | J73: Qualify:20%,Propose:20%,Negotiate:40%,Close:20% | K73: 4 | L73: 7 | M73: Yes
A74: E01 | B74: James Whitfield | C74: enterprise | D74: 02/02/2024 | E74: Q1 2024 | F74: 173863.85 | G74: 174099.98 | H74: 592266.18 | I74: 128173.95 | J74: Qualify:30%,Propose:25%,Negotiate:25%,Close:20% | K74: 4 | L74: 1 | M74: yes | N74: Two deals slipped to next week
A75: E02 | B75: Sarah Thornton | C75: Ent | D75: 2024-02-02 | E75: Q1 2024 | F75: 150050.1 | G75: 247923.93 | H75: 686983.79 | I75: 218143.07 | J75: Qualify:10%,Propose:35%,Negotiate:40%,Close:15% | K75: 2 | L75: 3 | M75: Yes | N75: Deal pulled forward from next quarter
A76: E03 | B76: Marcus Bellingham | C76: ENT | D76: 02 Feb 2024 | E76: Q1 2024 | F76: 123325.51 | G76: 129415.3 | H76: 587021.49 | I76: 173354.59 | J76: Qualify:5%,Propose:45%,Negotiate:30%,Close:20% | K76: 5 | L76: 8 | M76: N | N76: Budget freeze reported by prospect
A77: E04 | B77: Olivia Hargreaves | C77: Ent | D77: 02/02/2024 | E77: Q1 2024 | F77: 147282.69 | G77: 144247.78 | H77: 630149.36 | I77: 126783.04 | J77: Qualify:20%,Propose:35%,Negotiate:30%,Close:15% | K77: 1 | L77: 2 | M77: YES | N77: -
A78: E05 | B78: Richard Cavendish | C78: enterprise | D78: 02/02/2024 | E78: Q1 2024 | F78: 150281 | G78: 143927.79 | H78: 35491.14 | I78: 11451.57 | J78: Qualify:10%,Propose:35%,Negotiate:40%,Close:15% | K78: 6 | L78: 2 | M78: yes
A79: M01 | B79: Daniel Ashworth | C79: MidMarket | D79: 02/02/2024 | E79: Q1 2024 | F79: 33795.22 | G79: 59374.13 | H79: £93882 | I79: 21705.12 | J79: Qualify:20%,Propose:20%,Negotiate:40%,Close:20% | K79: 1 | L79: 7 | M79: y | N79: Revised following manager review
A80: M02 | B80: Priya Mehta | C80: MM | D80: 02/02/2024 | E80: Q1 2024 | F80: 30093.86 | G80: 28765.06 | H80: 89327.15 | I80: 24028.32 | J80: Qualify:20%,Propose:35%,Negotiate:30%,Close:15% | K80: 3 | L80: 7 | M80: y | N80: N/A
A81: M03 | B81: Tom Baxter | C81: Mid market | D81: 02.02.2024 | E81: Q1 2024 | F81: 69079.11 | G81: 38031.07 | H81: 195737.32 | I81: 46497.99 | J81: Qualify:25%,Propose:30%,Negotiate:35%,Close:10% | K81: 6 | L81: 6 | M81: Y | N81: New logo opportunity added
A82: M07 | B82: Andrew Collinson | C82: Mid market | D82: 2024-02-02 | E82: Q1 2024 | F82: 60923.02 | G82: 69862.66 | H82: 190889.13 | I82: 40561.57 | J82: Qualify:10%,Propose:35%,Negotiate:40%,Close:15% | K82: 3 | L82: 8 | M82: Yes | N82: n/a
A83: S01 | B83: Lucy Drummond | C83: SMB | D83: 02/02/24 | E83: Q1 2024 | F83: 21397.49 | G83: 21370.99 | H83: 81271.71 | I83: 24674.4 | J83: Qualify:10%,Propose:35%,Negotiate:40%,Close:15% | K83: 3 | L83: 14 | M83: yes | N83: Large renewal included
A84: S02 | B84: Ben Hartley | C84: Smb | D84: 02/02/2024 | E84: Q1-2024 | F84: 24261.15 | G84: 12171.34 | H84: 77305.44 | I84: 26372.27 | J84: Qualify:15%,Propose:40%,Negotiate:25%,Close:20% | K84: 3 | L84: 8 | M84: Y | N84: N/A
A85: S03 | B85: Fiona McKenzie | C85: Smb | D85: 02 Feb 2024 | E85: Q1 2024 | F85: 33635.61 | G85: 25771.36 | H85: £141190 | I85: 34343.55 | J85: Qualify:10%,Propose:35%,Negotiate:40%,Close:15% | K85: 3 | L85: 4 | M85: n
A86: S04 | B86: Callum Reid | C86: SMB | D86: 02.02.2024 | E86: Q1 2024 | F86: 23165.16 | G86: 20405.92 | H86: 98685.78 | I86: 28028.65 | J86: Qualify:25%,Propose:30%,Negotiate:35%,Close:10% | K86: 9 | L86: 6 | M86: yes | N86: N/A
A87: S05 | B87: Amara Osei | C87: SMB | D87: 02-02-2024 | E87: Q1 2024 | F87: 22849.92 | G87: 20454.82 | H87: 1057958 | I87: 35708.91 | J87: Qualify:25%,Propose:30%,Negotiate:35%,Close:10% | K87: 12 | L87: 6 | M87: YES | N87: none
A88: S06 | B88: Steven Bowman | C88: S M B | D88: 02/02/2024 | E88: Q1 2024 | F88: 29960.19 | G88: 15801.94 | H88: 128744.17 | I88: 40008.28 | J88: Qualify:20%,Propose:20%,Negotiate:40%,Close:20% | K88: 11 | L88: 13 | M88: YES
A89: S07 | B89: Rachel Sutton | C89: Smb | D89: 02/02/24 | E89: Q1 | F89: 34089.14 | G89: 32940.65 | H89: 89945.3 | I89: 18529.87 | J89: Qualify:30%,Propose:25%,Negotiate:25%,Close:20% | K89: 4 | L89: 15 | M89: yes
A90: E01 | B90: James Whitfield | C90: Enterprise | D90: 09/02/2024 | E90: Q1 2024 | F90: 169738.24 | G90: 172231.58 | H90: 496993.83 | I90: 165668 | J90: Qualify:30%,Propose:25%,Negotiate:25%,Close:20% | K90: 3 | L90: 3 | M90: y | N90: -
A91: E02 | B91: Sarah Thornton | C91: enterprise | D91: 09.02.2024 | E91: Q1 2024 | F91: 62796.07 | G91: 109199.17 | H91: 232807.78 | I91: 69015.5 | J91: Qualify:25%,Propose:30%,Negotiate:35%,Close:10% | K91: 3 | L91: 5 | M91: Yes | N91: N/A
A92: E03 | B92: Marcus Bellingham | C92: ENT | D92: 09 Feb 2024 | E92: q1 2024 | F92: 98307.26 | G92: 96270.97 | H92: 324196.68 | I92: 73096.68 | J92: Qualify:30%,Propose:25%,Negotiate:25%,Close:20% | K92: 2 | L92: 2 | M92: Yes | N92: n/a
A93: E04 | B93: Olivia Hargreaves | C93: enterprise | D93: 2024-02-09 | E93: Q1 2024 | F93: 102307.94 | G93: 110426.59 | H93: 383337.54 | I93: 70511.1 | J93: Qualify:25%,Propose:30%,Negotiate:35%,Close:10% | K93: 4 | L93: 8 | M93: yes
A94: E06 | B94: Helena Forsythe | C94: ENTERPRISE | D94: 09/02/24 | E94: Q1 2024 | F94: 98750.89 | G94: 95029.53 | H94: 435456.07 | I94: 108036.16 | J94: Qualify:20%,Propose:20%,Negotiate:40%,Close:20% | K94: 5 | L94: 6 | M94: YES
A95: M01 | B95: Daniel Ashworth | C95: mid-market | D95: 2024-02-09 | E95: Jan-Mar 2024 | F95: 63768.74 | G95: 110707.57 | H95: 279779.79 | I95: 74575.54 | J95: Qualify:30%,Propose:25%,Negotiate:25%,Close:20% | K95: 5 | L95: 6 | M95: Yes | N95: n/a
A96: M02 | B96: Priya Mehta | C96: MidMarket | D96: 09/02/2024 | E96: Q1 2024 | F96: 89436.94 | G96: 95858.14 | H96: 356344.66 | I96: 95019.8 | J96: Qualify:20%,Propose:20%,Negotiate:40%,Close:20% | K96: 4 | L96: 5 | M96: YES | N96: Pipeline updated post-QBR
A97: M03 | B97: Tom Baxter | C97: mid-market | D97: 09-02-2024 | E97: Q1 2024 | F97: 64176.21 | G97: 33309.84 | H97: 276182k | I97: 57718.53 | J97: Qualify:10%,Propose:35%,Negotiate:40%,Close:15% | K97: 6 | L97: 4 | M97: Y | N97: Revised following manager review
A98: M04 | B98: Claire Pemberton | C98: Mid Market | D98: 09.02.2024 | E98: Q1 2024 | F98: 42233.5 | G98: 42256.55 | H98: 197739.12 | I98: 37686.67 | J98: Qualify:25%,Propose:30%,Negotiate:35%,Close:10% | K98: 2 | L98: 8 | M98: y | N98: Budget freeze reported by prospect
A99: M05 | B99: Nathan Griffiths | C99: Mid Market | D99: 09.02.2024 | E99: Q1 2024 | F99: 41535.85 | G99: 38377.29 | H99: 127189.73 | I99: 29329.25 | J99: Qualify:20%,Propose:20%,Negotiate:40%,Close:20% | K99: 3 | L99: 5 | M99: Y
A100: M06 | B100: Yasmin Khalid | C100: Mid Market | D100: 09.02.2024 | E100: Q1 2024 | F100: 88809.63 | G100: 97292.13 | H100: 286511.56 | I100: 86355.74 | J100: Qualify:20%,Propose:35%,Negotiate:30%,Close:15% | K100: 3 | L100: 3 | M100: Late
...

Sheet Cleaned_Forecast_Data
A1: Rep_ID | B1: Rep_Name | C1: Segment | D1: Week_Ending_Date | E1: Quarter | F1: Forecasted_Revenue | G1: Actual_Revenue_Closed | H1: Pipeline_Value | I1: Weighted_Pipeline | J1: Deal_Count_Forecasted | K1: Deal_Count_Closed | L1: Forecast_Submitted_On_Time | M1: Notes_Clean2 | N1: Low_Pipeline_Flag
A2: E01 | B2: James Whitfield | C2: Enterprise | D2: 45296 | E2: Q1 2024 | F2: 83501.51 | G2: 80495.84 | H2: 237882.83 | I2: 72771.57 | J2: 5 | K2: 4 | L2: Yes | N2: OK
A3: E02 | B3: Sarah Thornton | C3: Enterprise | D3: 45296 | E3: Q1 2024 | F3: 101890.04 | G3: 187730.93 | H3: 432558.75 | I3: 89293.76 | J3: 3 | K3: 3 | L3: Yes | M3: Verbal commit received – awaiting paperwork | N3: OK
A4: E03 | B4: Marcus Bellingham | C4: Enterprise | D4: 45296 | E4: Q1 2024 | F4: 196116.65 | G4: 199835.64 | H4: 773362.56 | I4: 145229.87 | J4: 2 | K4: 6 | L4: Yes | M4: Budget freeze reported by prospect | N4: OK
A5: E04 | B5: Olivia Hargreaves | C5: Enterprise | D5: 45296 | E5: Q1 2024 | F5: 175696.67 | G5: 163648.17 | H5: 673858.18 | I5: 174249.1 | J5: 3 | K5: 3 | L5: No | N5: OK
A6: E05 | B6: Richard Cavendish | C6: Enterprise | D6: 45296 | E6: Q1 2024 | F6: 109537.6 | G6: 117300.04 | H6: 332070.5 | I6: 109714.81 | J6: 6 | K6: 6 | L6: Yes | M6: Revised following manager review | N6: OK
A7: E06 | B7: Helena Forsythe | C7: Enterprise | D7: 45296 | E7: Q1 2024 | F7: 92727.32 | G7: 86008.17 | H7: 267249 | I7: 79020.88 | J7: 5 | K7: 2 | L7: Yes | N7: OK
A8: M01 | B8: Daniel Ashworth | C8: Mid-Market | D8: 45296 | E8: Q1 2024 | F8: 58658.74 | G8: 93144.86 | H8: 286520.93 | I8: 64403.07 | J8: 5 | K8: 1 | L8: Yes | N8: OK
A9: M02 | B9: Priya Mehta | C9: Mid-Market | D9: 45296 | E9: Q1 2024 | F9: 65936.68 | G9: 65711.28 | H9: 317995.87 | I9: 102198.51 | J9: 3 | K9: 2 | L9: Yes | N9: OK
A10: M03 | B10: Tom Baxter | C10: Mid-Market | D10: 45296 | E10: Q1 2024 | F10: 543030 | G10: 30943.06 | H10: 2325305 | I10: 68408.93 | J10: 3 | K10: 4 | L10: Yes | M10: Verbal commit received – awaiting paperwork | N10: OK
A11: M04 | B11: Claire Pemberton | C11: Mid-Market | D11: 45296 | E11: Q1 2024 | F11: 81578.12 | G11: 71075.53 | H11: 260739.44 | I11: 70835.02 | J11: 6 | K11: 4 | L11: No | N11: OK
A12: M05 | B12: Nathan Griffiths | C12: Mid-Market | D12: 45296 | E12: Q1 2024 | F12: 81830.2 | G12: 70885.53 | H12: 216975.38 | I12: 68586.08 | J12: 1 | K12: 2 | L12: Yes | N12: OK
A13: M06 | B13: Yasmin Khalid | C13: Mid-Market | D13: 45296 | E13: Q1 2024 | F13: 69128.69 | G13: 69970.43 | H13: 340285.35 | I13: 110347.15 | J13: 2 | K13: 1 | L13: Yes | M13: Forecast includes upsell opportunity | N13: OK
A14: M07 | B14: Andrew Collinson | C14: Mid-Market | D14: 45296 | E14: Q1 2024 | F14: 87439.06 | G14: 100434.85 | H14: 252435.87 | I14: 87009.74 | J14: 5 | K14: 8 | L14: Yes | M14: Verbal commit received – awaiting paperwork | N14: OK
A15: S01 | B15: Lucy Drummond | C15: SMB | D15: 45296 | E15: Q1 2024 | F15: 9850.08 | G15: 7722.27 | H15: 30417.13 | I15: 10078.68 | J15: 5 | K15: 15 | L15: Yes | N15: OK
A16: S02 | B16: Ben Hartley | C16: SMB | D16: 45296 | E16: Q1 2024 | F16: 24852.66 | G16: 12914.1 | H16: 4330.13 | I16: 1193.85 | J16: 3 | K16: 14 | L16: Yes | N16: FLAG
A17: S03 | B17: Fiona McKenzie | C17: SMB | D17: 45296 | E17: Q1 2024 | F17: 24515.3 | G17: 30487.63 | H17: 93706.1 | I17: 25701.93 | J17: 12 | K17: 12 | L17: Yes | M17: Budget freeze reported by prospect | N17: OK
A18: S04 | B18: Callum Reid | C18: SMB | D18: 45296 | E18: Q1 2024 | F18: 14780.27 | G18: 17796.63 | H18: 40361.18 | I18: 9163.43 | J18: 2 | K18: 2 | L18: Yes | M18: Revised following manager review | N18: OK
A19: S05 | B19: Amara Osei | C19: SMB | D19: 45296 | E19: Q1 2024 | F19: 30534.07 | G19: 31793.74 | H19: 3753.56 | I19: 1271.05 | J19: 2 | K19: 4 | L19: No | M19: Revised following manager review | N19: FLAG
A20: S06 | B20: Steven Bowman | C20: SMB | D20: 45296 | E20: Q1 2024 | F20: 19860.67 | G20: 9686 | H20: 50882.36 | I20: 12032.23 | J20: 8 | K20: 8 | L20: Yes | N20: OK
A21: S07 | B21: Rachel Sutton | C21: SMB | D21: 45296 | E21: Q1 2024 | F21: 29474.33 | G21: 25459.86 | H21: 122320 | I21: 27811.19 | J21: 3 | K21: 2 | L21: No | N21: OK
A22: E01 | B22: James Whitfield | C22: Enterprise | D22: 45303 | E22: Q1 2024 | F22: 117165.29 | G22: 109824.23 | H22: 394169.55 | I22: 100192.76 | J22: 5 | K22: 7 | L22: Yes | M22: New logo opportunity added | N22: OK
A23: E02 | B23: Sarah Thornton | C23: Enterprise | D23: 45303 | E23: Q1 2024 | F23: 68871.99 | G23: 111983.87 | H23: 296107.25 | I23: 68868.15 | J23: 4 | K23: 2 | L23: Yes | M23: Forecast includes upsell opportunity | N23: OK
A24: E03 | B24: Marcus Bellingham | C24: Enterprise | D24: 45303 | E24: Q1 2024 | F24: 196721.52 | G24: 190548.4 | H24: 703224.44 | I24: 204849.25 | J24: 4 | K24: 4 | L24: Yes | M24: Deal pulled forward from next quarter | N24: OK
A25: E04 | B25: Olivia Hargreaves | C25: Enterprise | D25: 45303 | E25: Q1 2024 | F25: 111449.69 | G25: 106084.59 | H25: 291500 | I25: 82761.82 | J25: 1 | K25: 1 | L25: Yes | N25: OK
A26: E05 | B26: Richard Cavendish | C26: Enterprise | D26: 45303 | E26: Q1 2024 | F26: 192575.38 | G26: 198611.83 | H26: 505615.51 | I26: 163929.23 | J26: 4 | K26: 8 | L26: Yes | N26: OK
A27: E06 | B27: Helena Forsythe | C27: Enterprise | D27: 45303 | E27: Q1 2024 | F27: 184111.76 | G27: 183365.72 | H27: 806306.78 | I27: 183146.88 | J27: 5 | K27: 5 | L27: Yes | M27: Revised following manager review | N27: OK
A28: M01 | B28: Daniel Ashworth | C28: Mid-Market | D28: 45303 | E28: Q1 2024 | F28: 56849.47 | G28: 90344.27 | H28: 201215.05 | I28: 50590.37 | J28: 5 | K28: 8 | L28: No | N28: OK
A29: M02 | B29: Priya Mehta | C29: Mid-Market | D29: 45303 | E29: Q1 2024 | F29: 74078.04 | G29: 80742.14 | H29: 275612.82 | I29: 72364.66 | J29: 4 | K29: 4 | L29: Yes | M29: Pipeline updated post-QBR | N29: OK
A30: M03 | B30: Tom Baxter | C30: Mid-Market | D30: 45303 | E30: Q1 2024 | F30: 73444.33 | G30: 38100.26 | H30: 222473.95 | I30: 68835.45 | J30: 4 | K30: 6 | L30: Yes | M30: Two deals slipped to next week | N30: OK
A31: M04 | B31: Claire Pemberton | C31: Mid-Market | D31: 45303 | E31: Q1 2024 | F31: 86976.7 | G31: 79132.12 | H31: 352546.08 | I31: 91840.15 | J31: 1 | K31: 1 | L31: Yes | M31: Forecast includes upsell opportunity | N31: OK
A32: M07 | B32: Andrew Collinson | C32: Mid-Market | D32: 45303 | E32: Q1 2024 | F32: 70640.84 | G32: 80350.55 | H32: 342867.77 | I32: 96228.12 | J32: 6 | K32: 7 | L32: Yes | N32: OK
A33: S02 | B33: Ben Hartley | C33: SMB | D33: 45303 | E33: Q1 2024 | F33: 28375.2 | G33: 16264.33 | H33: 121113.07 | I33: 36908.63 | J33: 12 | K33: 9 | L33: Yes | M33: Budget freeze reported by prospect | N33: OK
A34: S03 | B34: Fiona McKenzie | C34: SMB | D34: 45303 | E34: Q1 2024 | F34: 14584.31 | G34: 14326.96 | H34: 610823 | I34: 16059.35 | J34: 7 | K34: 11 | L34: Yes | N34: OK
A35: S04 | B35: Callum Reid | C35: SMB | D35: 45303 | E35: Q1 2024 | F35: 28470.45 | G35: 31183.81 | H35: 121842.29 | I35: 22288.78 | J35: 6 | K35: 12 | L35: Yes | N35: OK
A36: S05 | B36: Amara Osei | C36: SMB | D36: 45303 | E36: Q1 2024 | F36: 14787.9 | G36: 11983.05 | H36: 48635.48 | I36: 16616.27 | J36: 4 | K36: 5 | L36: Yes | M36: Budget freeze reported by prospect | N36: OK
A37: S07 | B37: Rachel Sutton | C37: SMB | D37: 45303 | E37: Q1 2024 | F37: 15887.69 | G37: 19415.47 | H37: 74213.83 | I37: 24369.03 | J37: 11 | K37: 12 | L37: Yes | N37: OK
A38: E01 | B38: James Whitfield | C38: Enterprise | D38: 45310 | E38: Q1 2024 | F38: 168122.4 | G38: 156114.67 | H38: 761233.88 | I38: 148045.34 | J38: 2 | K38: 3 | L38: Yes | N38: OK
A39: E02 | B39: Sarah Thornton | C39: Enterprise | D39: 45310 | E39: Q1 2024 | F39: 116610.42 | G39: 203571.6 | H39: 368677.28 | I39: 81395.49 | J39: 5 | K39: 4 | L39: Yes | N39: OK
A40: E03 | B40: Marcus Bellingham | C40: Enterprise | D40: 45310 | E40: Q1 2024 | F40: 112679.33 | G40: 108434.56 | H40: 401459.27 | I40: 116462.49 | J40: 3 | K40: 4 | L40: Yes | M40: Forecast includes upsell opportunity | N40: OK
A41: E04 | B41: Olivia Hargreaves | C41: Enterprise | D41: 45310 | E41: Q1 2024 | F41: 211974.67 | G41: 211990.69 | H41: 7619241 | I41: 252349.73 | J41: 6 | K41: 8 | L41: Yes | M41: Two deals slipped to next week | N41: OK
A42: E05 | B42: Richard Cavendish | C42: Enterprise | D42: 45310 | E42: Q1 2024 | F42: 104526.7 | G42: 104843.86 | H42: 500701.92 | I42: 139949.21 | J42: 6 | K42: 8 | L42: Yes | M42: Forecast includes upsell opportunity | N42: OK
A43: E06 | B43: Helena Forsythe | C43: Enterprise | D43: 45310 | E43: Q1 2024 | F43: 136063.32 | G43: 141734.43 | H43: 494871.09 | I43: 116273.2 | J43: 4 | K43: 1 | L43: Yes | M43: Two deals slipped to next week | N43: OK
A44: M01 | B44: Daniel Ashworth | C44: Mid-Market | D44: 45310 | E44: Q1 2024 | F44: 47604.46 | G44: 82137.37 | H44: 122446.94 | I44: 38678.95 | J44: 6 | K44: 2 | L44: Yes | M44: Revised following manager review | N44: OK
A45: M02 | B45: Priya Mehta | C45: Mid-Market | D45: 45310 | E45: Q1 2024 | F45: 72996.2 | G45: 73190.49 | H45: 258313.54 | I45: 67233.17 | J45: 4 | K45: 5 | L45: Yes | M45: Pipeline updated post-QBR | N45: OK
A46: M03 | B46: Tom Baxter | C46: Mid-Market | D46: 45310 | E46: Q1 2024 | F46: 67073.43 | G46: 34193.52 | H46: 242562 | I46: 57369.56 | J46: 5 | K46: 3 | L46: Yes | N46: OK
A47: M04 | B47: Claire Pemberton | C47: Mid-Market | D47: 45310 | E47: Q1 2024 | F47: 69821.33 | G47: 76539.84 | H47: 10505.19 | I47: 2944.93 | J47: 1 | K47: 3 | L47: Yes | M47: Budget freeze reported by prospect | N47: FLAG
A48: M05 | B48: Nathan Griffiths | C48: Mid-Market | D48: 45310 | E48: Q1 2024 | F48: 71562.28 | G48: 74779.07 | H48: 331394.4 | I48: 81059.6 | J48: 3 | K48: 6 | L48: Yes | N48: OK
A49: M06 | B49: Yasmin Khalid | C49: Mid-Market | D49: 45310 | E49: Q1 2024 | F49: 75622.18 | G49: 80247.78 | H49: 272935.3 | I49: 91046.33 | J49: 1 | K49: 2 | L49: Yes | M49: Large renewal included | N49: OK
A50: M07 | B50: Andrew Collinson | C50: Mid-Market | D50: 45310 | E50: Q1 2024 | F50: 82250.38 | G50: 85204.24 | H50: 307959.24 | I50: 67588.44 | J50: 6 | K50: 4 | L50: Yes | N50: OK
A51: S01 | B51: Lucy Drummond | C51: SMB | D51: 45310 | E51: Q1 2024 | F51: 33974.78 | G51: 37207.72 | H51: 156734.51 | I51: 38462.31 | J51: 9 | K51: 9 | L51: Yes | M51: Pipeline updated post-QBR | N51: OK
A52: S02 | B52: Ben Hartley | C52: SMB | D52: 45310 | E52: Q1 2024 | F52: 34601.61 | G52: 19326.16 | H52: 158547.95 | I52: 49447.29 | J52: 5 | K52: 9 | L52: Yes | M52: Customer procurement delay | N52: OK
A53: S03 | B53: Fiona McKenzie | C53: SMB | D53: 45310 | E53: Q1 2024 | F53: 25451.2 | G53: 23019.75 | H53: 65750.91 | I53: 13304.04 | J53: 6 | K53: 9 | L53: Yes | M53: Large renewal included | N53: OK
A54: S04 | B54: Callum Reid | C54: SMB | D54: 45310 | E54: Q1 2024 | F54: 30266.62 | G54: 29991.92 | H54: 97998 | I54: 31038.17 | J54: 9 | K54: 14 | L54: No | N54: OK
A55: S05 | B55: Amara Osei | C55: SMB | D55: 45310 | E55: Q1 2024 | F55: 26153.2 | G55: 27258.96 | H55: 107133.27 | I55: 31574.56 | J55: 9 | K55: 15 | L55: Yes | M55: Revised following manager review | N55: OK
A56: E01 | B56: James Whitfield | C56: Enterprise | D56: 45317 | E56: Q1 2024 | F56: 96256.87 | G56: 92172.5 | H56: 334166.74 | I56: 114082.77 | J56: 6 | K56: 3 | L56: No | N56: OK
A57: E02 | B57: Sarah Thornton | C57: Enterprise | D57: 45317 | E57: Q1 2024 | F57: 108646.46 | G57: 191640.54 | H57: 419501 | I57: 101089.27 | J57: 4 | K57: 6 | L57: Yes | M57: Revised following manager review | N57: OK
A58: E03 | B58: Marcus Bellingham | C58: Enterprise | D58: 45317 | E58: Q1 2024 | F58: 108728.78 | G58: 114466.49 | H58: 431213.75 | I58: 94698.75 | J58: 2 | K58: 4 | L58: Yes | M58: Pipeline updated post-QBR | N58: OK
A59: E04 | B59: Olivia Hargreaves | C59: Enterprise | D59: 45317 | E59: Q1 2024 | F59: 130153.92 | G59: 136160.4 | H59: 330519.72 | I59: 66615.9 | J59: 4 | K59: 6 | L59: Yes | N59: OK
A60: E05 | B60: Richard Cavendish | C60: Enterprise | D60: 45317 | E60: Q1 2024 | F60: 170067.7 | G60: 157309.91 | H60: 785414.52 | I60: 155789.73 | J60: 6 | K60: 8 | L60: No | N60: OK
A61: E06 | B61: Helena Forsythe | C61: Enterprise | D61: 45317 | E61: Q1 2024 | F61: 154277.96 | G61: 153135.45 | H61: 423947.52 | I61: 137772.25 | J61: 6 | K61: 7 | L61: Yes | M61: Customer procurement delay | N61: OK
A62: M01 | B62: Daniel Ashworth | C62: Mid-Market | D62: 45317 | E62: Q1 2024 | F62: 34352.23 | G62: 63524.22 | H62: 91646.03 | I62: 17948.79 | J62: 1 | K62: 8 | L62: Yes | N62: OK
A63: M02 | B63: Priya Mehta | C63: Mid-Market | D63: 45317 | E63: Q1 2024 | F63: 73263.64 | G63: 83558.62 | H63: 247566.3 | I63: 53515.32 | J63: 6 | K63: 5 | L63: Yes | N63: OK
A64: M03 | B64: Tom Baxter | C64: Mid-Market | D64: 45317 | E64: Q1 2024 | F64: 95500.52 | G64: 51958.3 | H64: 245663.9 | I64: 76059.91 | J64: 3 | K64: 5 | L64: Yes | N64: OK
A65: M04 | B65: Claire Pemberton | C65: Mid-Market | D65: 45317 | E65: Q1 2024 | F65: 39444.56 | G65: 37215.59 | H65: 175216.23 | I65: 34069.52 | J65: 1 | K65: 6 | L65: Yes | N65: OK
A66: M06 | B66: Yasmin Khalid | C66: Mid-Market | D66: 45317 | E66: Q1 2024 | F66: 46994.79 | G66: 49511.17 | H66: 179394.86 | I66: 39016.25 | J66: 5 | K66: 8 | L66: Yes | N66: OK
A67: M07 | B67: Andrew Collinson | C67: Mid-Market | D67: 45317 | E67: Q1 2024 | F67: 43806.64 | G67: 44578.39 | H67: 1127410 | I67: 21978.15 | J67: 1 | K67: 6 | L67: Yes | N67: OK
A68: S01 | B68: Lucy Drummond | C68: SMB | D68: 45317 | E68: Q1 2024 | F68: 26619.47 | G68: 24780.77 | H68: 122748 | I68: 34382.71 | J68: 10 | K68: 8 | L68: Yes | N68: OK
A69: S02 | B69: Ben Hartley | C69: SMB | D69: 45317 | E69: Q1 2024 | F69: 44533.9 | G69: 22469.51 | H69: 133297.94 | I69: 41220.6 | J69: 12 | K69: 6 | L69: Yes | N69: OK
A70: S03 | B70: Fiona McKenzie | C70: SMB | D70: 45317 | E70: Q1 2024 | F70: 9843.73 | G70: 9559.28 | H70: 44206.46 | I70: 10602.04 | J70: 3 | K70: 6 | L70: Yes | N70: OK
A71: S04 | B71: Callum Reid | C71: SMB | D71: 45317 | E71: Q1 2024 | F71: 23668.89 | G71: 29044.47 | H71: 112183.27 | I71: 35637.11 | J71: 12 | K71: 13 | L71: Yes | M71: Large renewal included | N71: OK
A72: S06 | B72: Steven Bowman | C72: SMB | D72: 45317 | E72: Q1 2024 | F72: 47303.09 | G72: 24236.03 | H72: 164072.72 | I72: 48469.15 | J72: 2 | K72: 6 | L72: Yes | M72: Revised following manager review | N72: OK
A73: S07 | B73: Rachel Sutton | C73: SMB | D73: 45317 | E73: Q1 2024 | F73: 23733.97 | G73: 19478.8 | H73: 77742.49 | I73: 22744.57 | J73: 4 | K73: 7 | L73: Yes | N73: OK
A74: E01 | B74: James Whitfield | C74: Enterprise | D74: 45324 | E74: Q1 2024 | F74: 173863.85 | G74: 174099.98 | H74: 592266.18 | I74: 128173.95 | J74: 4 | K74: 1 | L74: Yes | M74: Two deals slipped to next week | N74: OK
A75: E02 | B75: Sarah Thornton | C75: Enterprise | D75: 45324 | E75: Q1 2024 | F75: 150050.1 | G75: 247923.93 | H75: 686983.79 | I75: 218143.07 | J75: 2 | K75: 3 | L75: Yes | M75: Deal pulled forward from next quarter | N75: OK
A76: E03 | B76: Marcus Bellingham | C76: Enterprise | D76: 45324 | E76: Q1 2024 | F76: 123325.51 | G76: 129415.3 | H76: 587021.49 | I76: 173354.59 | J76: 5 | K76: 8 | L76: No | M76: Budget freeze reported by prospect | N76: OK
A77: E04 | B77: Olivia Hargreaves | C77: Enterprise | D77: 45324 | E77: Q1 2024 | F77: 147282.69 | G77: 144247.78 | H77: 630149.36 | I77: 126783.04 | J77: 1 | K77: 2 | L77: Yes | N77: OK
A78: E05 | B78: Richard Cavendish | C78: Enterprise | D78: 45324 | E78: Q1 2024 | F78: 150281 | G78: 143927.79 | H78: 35491.14 | I78: 11451.57 | J78: 6 | K78: 2 | L78: Yes | N78: FLAG
A79: M01 | B79: Daniel Ashworth | C79: Mid-Market | D79: 45324 | E79: Q1 2024 | F79: 33795.22 | G79: 59374.13 | H79: 93882 | I79: 21705.12 | J79: 1 | K79: 7 | L79: Yes | M79: Revised following manager review | N79: OK
A80: M02 | B80: Priya Mehta | C80: Mid-Market | D80: 45324 | E80: Q1 2024 | F80: 30093.86 | G80: 28765.06 | H80: 89327.15 | I80: 24028.32 | J80: 3 | K80: 7 | L80: Yes | N80: OK
A81: M03 | B81: Tom Baxter | C81: Mid-Market | D81: 45324 | E81: Q1 2024 | F81: 69079.11 | G81: 38031.07 | H81: 195737.32 | I81: 46497.99 | J81: 6 | K81: 6 | L81: Yes | M81: New logo opportunity added | N81: OK
A82: M07 | B82: Andrew Collinson | C82: Mid-Market | D82: 45324 | E82: Q1 2024 | F82: 60923.02 | G82: 69862.66 | H82: 190889.13 | I82: 40561.57 | J82: 3 | K82: 8 | L82: Yes | N82: OK
A83: S01 | B83: Lucy Drummond | C83: SMB | D83: 45324 | E83: Q1 2024 | F83: 21397.49 | G83: 21370.99 | H83: 81271.71 | I83: 24674.4 | J83: 3 | K83: 14 | L83: Yes | M83: Large renewal included | N83: OK
A84: S02 | B84: Ben Hartley | C84: SMB | D84: 45324 | E84: Q1 2024 | F84: 24261.15 | G84: 12171.34 | H84: 77305.44 | I84: 26372.27 | J84: 3 | K84: 8 | L84: Yes | N84: OK
A85: S03 | B85: Fiona McKenzie | C85: SMB | D85: 45324 | E85: Q1 2024 | F85: 33635.61 | G85: 25771.36 | H85: 141190 | I85: 34343.55 | J85: 3 | K85: 4 | L85: No | N85: OK
A86: S04 | B86: Callum Reid | C86: SMB | D86: 45324 | E86: Q1 2024 | F86: 23165.16 | G86: 20405.92 | H86: 98685.78 | I86: 28028.65 | J86: 9 | K86: 6 | L86: Yes | N86: OK
A87: S05 | B87: Amara Osei | C87: SMB | D87: 45324 | E87: Q1 2024 | F87: 22849.92 | G87: 20454.82 | H87: 1057958 | I87: 35708.91 | J87: 12 | K87: 6 | L87: Yes | N87: OK
A88: S06 | B88: Steven Bowman | C88: SMB | D88: 45324 | E88: Q1 2024 | F88: 29960.19 | G88: 15801.94 | H88: 128744.17 | I88: 40008.28 | J88: 11 | K88: 13 | L88: Yes | N88: OK
A89: S07 | B89: Rachel Sutton | C89: SMB | D89: 45324 | E89: Q1 2024 | F89: 34089.14 | G89: 32940.65 | H89: 89945.3 | I89: 18529.87 | J89: 4 | K89: 15 | L89: Yes | N89: OK
A90: E01 | B90: James Whitfield | C90: Enterprise | D90: 45331 | E90: Q1 2024 | F90: 169738.24 | G90: 172231.58 | H90: 496993.83 | I90: 165668 | J90: 3 | K90: 3 | L90: Yes | N90: OK
A91: E02 | B91: Sarah Thornton | C91: Enterprise | D91: 45331 | E91: Q1 2024 | F91: 62796.07 | G91: 109199.17 | H91: 232807.78 | I91: 69015.5 | J91: 3 | K91: 5 | L91: Yes | N91: OK
A92: E03 | B92: Marcus Bellingham | C92: Enterprise | D92: 45331 | E92: Q1 2024 | F92: 98307.26 | G92: 96270.97 | H92: 324196.68 | I92: 73096.68 | J92: 2 | K92: 2 | L92: Yes | N92: OK
A93: E04 | B93: Olivia Hargreaves | C93: Enterprise | D93: 45331 | E93: Q1 2024 | F93: 102307.94 | G93: 110426.59 | H93: 383337.54 | I93: 70511.1 | J93: 4 | K93: 8 | L93: Yes | N93: OK
A94: E06 | B94: Helena Forsythe | C94: Enterprise | D94: 45331 | E94: Q1 2024 | F94: 98750.89 | G94: 95029.53 | H94: 435456.07 | I94: 108036.16 | J94: 5 | K94: 6 | L94: Yes | N94: OK
A95: M01 | B95: Daniel Ashworth | C95: Mid-Market | D95: 45331 | E95: Q1 2024 | F95: 63768.74 | G95: 110707.57 | H95: 279779.79 | I95: 74575.54 | J95: 5 | K95: 6 | L95: Yes | N95: OK
A96: M02 | B96: Priya Mehta | C96: Mid-Market | D96: 45331 | E96: Q1 2024 | F96: 89436.94 | G96: 95858.14 | H96: 356344.66 | I96: 95019.8 | J96: 4 | K96: 5 | L96: Yes | M96: Pipeline updated post-QBR | N96: OK
A97: M03 | B97: Tom Baxter | C97: Mid-Market | D97: 45331 | E97: Q1 2024 | F97: 64176.21 | G97: 33309.84 | H97: 276182 | I97: 57718.53 | J97: 6 | K97: 4 | L97: Yes | M97: Revised following manager review | N97: OK
A98: M04 | B98: Claire Pemberton | C98: Mid-Market | D98: 45331 | E98: Q1 2024 | F98: 42233.5 | G98: 42256.55 | H98: 197739.12 | I98: 37686.67 | J98: 2 | K98: 8 | L98: Yes | M98: Budget freeze reported by prospect | N98: OK
A99: M05 | B99: Nathan Griffiths | C99: Mid-Market | D99: 45331 | E99: Q1 2024 | F99: 41535.85 | G99: 38377.29 | H99: 127189.73 | I99: 29329.25 | J99: 3 | K99: 5 | L99: Yes | N99: OK
A100: M06 | B100: Yasmin Khalid | C100: Mid-Market | D100: 45331 | E100: Q1 2024 | F100: 88809.63 | G100: 97292.13 | H100: 286511.56 | I100: 86355.74 | J100: 3 | K100: 3 | L100: No | N100: OK
...

Sheet Email_Summary
A1: Mertics | B1: Value
A2: Forecast_Accuracy_Pct | B2: =1-ABS(SUMIFS(Cleaned_Forecast_Data!F:F,Cleaned_Forecast_Data!E:E,"<>Q4 2024")-SUMIFS(Cleaned_Forecast_Data!G:G,Cleaned_Forecast_Data!E:E,"<>Q4 2024"))/SUMIFS(Cleaned_Forecast_Data!G:G,Cleaned_Forecast_Data!E:E,"<>Q4 2024") -> 0.4094198
A3: Total_Forecasted | B3: =SUMIFS(Cleaned_Forecast_Data!F:F,Cleaned_Forecast_Data!E:E,"<>Q4 2024") -> 73712330
A4: Total_Actual | B4: =SUMIFS(Cleaned_Forecast_Data!G:G,Cleaned_Forecast_Data!E:E,"<>Q4 2024") -> 46343045
A5: Miss_Amount | B5: =B3-B4 -> 27369285
A6: Weakest_Segment | B6: SMB
A7: Strongest_Segment | B7: Enterprise
A8: Q3_Miss_Amount | B8: =SUMIFS(Cleaned_Forecast_Data!F:F,Cleaned_Forecast_Data!E:E,"Q3 2024")-SUMIFS(Cleaned_Forecast_Data!G:G,Cleaned_Forecast_Data!E:E,"Q3 2024") -> 16616195

Sheet Analysis_Sheet
A1: Section - 1 Forecast Accuracy Summary by Rep (Q1 to Q3 2024 only — Q4 excluded as quarter not yet closed)
A3: Rep_ID | B3: Rep_Name | C3: Segment | D3: Total_Forecasted | E3: Total_Actual | F3: Forecast_Accuracy_Pct | G3: Bias | H3: Total Submissions | I3: On Time %
A4: E01 | B4: James Whitfield | C4: Enterprise | D4: =SUMIFS(RAW_Forecast_Data!F:F,RAW_Forecast_Data!A:A,A4,RAW_Forecast_Data!E:E,"<>Q4 2024") -> 19225747 | E4: =SUMIFS(RAW_Forecast_Data!G:G,RAW_Forecast_Data!A:A,A4,RAW_Forecast_Data!E:E,"<>Q4 2024") -> 4793418.1 | F4: =IFERROR(1-ABS(D4-E4)/E4,"") -> -2.0108637 | G4: =IF(D4>E4,"Over-Forecaster","Under-Forecaster") -> Over-Forecaster | H4: =COUNTIF(RAW_Forecast_Data!A:A,A4) -> 50 | I4: =IFERROR(COUNTIFS(RAW_Forecast_Data!A:A,A4,RAW_Forecast_Data!M:M,"Yes")/H4,"") -> 0.46
A5: E02 | B5: Sarah Thornton | C5: Enterprise | D5: =SUMIFS(RAW_Forecast_Data!F:F,RAW_Forecast_Data!A:A,A5,RAW_Forecast_Data!E:E,"<>Q4 2024") -> 4452816.2 | E5: =SUMIFS(RAW_Forecast_Data!G:G,RAW_Forecast_Data!A:A,A5,RAW_Forecast_Data!E:E,"<>Q4 2024") -> 5916007.8 | F5: =IFERROR(1-ABS(D5-E5)/E5,"") -> 0.75267248 | G5: =IF(D5>E5,"Over-Forecaster","Under-Forecaster") -> Under-Forecaster | H5: =COUNTIF(RAW_Forecast_Data!A:A,A5) -> 51 | I5: =IFERROR(COUNTIFS(RAW_Forecast_Data!A:A,A5,RAW_Forecast_Data!M:M,"Yes")/H5,"") -> 0.50980392
A6: E03 | B6: Marcus Bellingham | C6: Enterprise | D6: =SUMIFS(RAW_Forecast_Data!F:F,RAW_Forecast_Data!A:A,A6,RAW_Forecast_Data!E:E,"<>Q4 2024") -> 5471677 | E6: =SUMIFS(RAW_Forecast_Data!G:G,RAW_Forecast_Data!A:A,A6,RAW_Forecast_Data!E:E,"<>Q4 2024") -> 4481642.6 | F6: =IFERROR(1-ABS(D6-E6)/E6,"") -> 0.77909116 | G6: =IF(D6>E6,"Over-Forecaster","Under-Forecaster") -> Over-Forecaster | H6: =COUNTIF(RAW_Forecast_Data!A:A,A6) -> 50 | I6: =IFERROR(COUNTIFS(RAW_Forecast_Data!A:A,A6,RAW_Forecast_Data!M:M,"Yes")/H6,"") -> 0.48
A7: E04 | B7: Olivia Hargreaves | C7: Enterprise | D7: =SUMIFS(RAW_Forecast_Data!F:F,RAW_Forecast_Data!A:A,A7,RAW_Forecast_Data!E:E,"<>Q4 2024") -> 5680832.5 | E7: =SUMIFS(RAW_Forecast_Data!G:G,RAW_Forecast_Data!A:A,A7,RAW_Forecast_Data!E:E,"<>Q4 2024") -> 5029247.9 | F7: =IFERROR(1-ABS(D7-E7)/E7,"") -> 0.87044094 | G7: =IF(D7>E7,"Over-Forecaster","Under-Forecaster") -> Over-Forecaster | H7: =COUNTIF(RAW_Forecast_Data!A:A,A7) -> 51 | I7: =IFERROR(COUNTIFS(RAW_Forecast_Data!A:A,A7,RAW_Forecast_Data!M:M,"Yes")/H7,"") -> 0.54901961
A8: E05 | B8: Richard Cavendish | C8: Enterprise | D8: =SUMIFS(RAW_Forecast_Data!F:F,RAW_Forecast_Data!A:A,A8,RAW_Forecast_Data!E:E,"<>Q4 2024") -> 6035497.9 | E8: =SUMIFS(RAW_Forecast_Data!G:G,RAW_Forecast_Data!A:A,A8,RAW_Forecast_Data!E:E,"<>Q4 2024") -> 4989297.1 | F8: =IFERROR(1-ABS(D8-E8)/E8,"") -> 0.79031098 | G8: =IF(D8>E8,"Over-Forecaster","Under-Forecaster") -> Over-Forecaster | H8: =COUNTIF(RAW_Forecast_Data!A:A,A8) -> 50 | I8: =IFERROR(COUNTIFS(RAW_Forecast_Data!A:A,A8,RAW_Forecast_Data!M:M,"Yes")/H8,"") -> 0.6
A9: E06 | B9: Helena Forsythe | C9: Enterprise | D9: =SUMIFS(RAW_Forecast_Data!F:F,RAW_Forecast_Data!A:A,A9,RAW_Forecast_Data!E:E,"<>Q4 2024") -> 6824711.6 | E9: =SUMIFS(RAW_Forecast_Data!G:G,RAW_Forecast_Data!A:A,A9,RAW_Forecast_Data!E:E,"<>Q4 2024") -> 4227008.8 | F9: =IFERROR(1-ABS(D9-E9)/E9,"") -> 0.38545127 | G9: =IF(D9>E9,"Over-Forecaster","Under-Forecaster") -> Over-Forecaster | H9: =COUNTIF(RAW_Forecast_Data!A:A,A9) -> 47 | I9: =IFERROR(COUNTIFS(RAW_Forecast_Data!A:A,A9,RAW_Forecast_Data!M:M,"Yes")/H9,"") -> 0.55319149
A10: M01 | B10: Daniel Ashworth | C10: Mid-Market | D10: =SUMIFS(RAW_Forecast_Data!F:F,RAW_Forecast_Data!A:A,A10,RAW_Forecast_Data!E:E,"<>Q4 2024") -> 1767849.6 | E10: =SUMIFS(RAW_Forecast_Data!G:G,RAW_Forecast_Data!A:A,A10,RAW_Forecast_Data!E:E,"<>Q4 2024") -> 2305549.9 | F10: =IFERROR(1-ABS(D10-E10)/E10,"") -> 0.76678001 | G10: =IF(D10>E10,"Over-Forecaster","Under-Forecaster") -> Under-Forecaster | H10: =COUNTIF(RAW_Forecast_Data!A:A,A10) -> 50 | I10: =IFERROR(COUNTIFS(RAW_Forecast_Data!A:A,A10,RAW_Forecast_Data!M:M,"Yes")/H10,"") -> 0.56
A11: M02 | B11: Priya Mehta | C11: Mid-Market | D11: =SUMIFS(RAW_Forecast_Data!F:F,RAW_Forecast_Data!A:A,A11,RAW_Forecast_Data!E:E,"<>Q4 2024") -> 2867670.5 | E11: =SUMIFS(RAW_Forecast_Data!G:G,RAW_Forecast_Data!A:A,A11,RAW_Forecast_Data!E:E,"<>Q4 2024") -> 1945103.2 | F11: =IFERROR(1-ABS(D11-E11)/E11,"") -> 0.52569755 | G11: =IF(D11>E11,"Over-Forecaster","Under-Forecaster") -> Over-Forecaster | H11: =COUNTIF(RAW_Forecast_Data!A:A,A11) -> 49 | I11: =IFERROR(COUNTIFS(RAW_Forecast_Data!A:A,A11,RAW_Forecast_Data!M:M,"Yes")/H11,"") -> 0.44897959
A12: M03 | B12: Tom Baxter | C12: Mid-Market | D12: =SUMIFS(RAW_Forecast_Data!F:F,RAW_Forecast_Data!A:A,A12,RAW_Forecast_Data!E:E,"<>Q4 2024") -> 4555593.9 | E12: =SUMIFS(RAW_Forecast_Data!G:G,RAW_Forecast_Data!A:A,A12,RAW_Forecast_Data!E:E,"<>Q4 2024") -> 1377349.9 | F12: =IFERROR(1-ABS(D12-E12)/E12,"") -> -1.3075067 | G12: =IF(D12>E12,"Over-Forecaster","Under-Forecaster") -> Over-Forecaster | H12: =COUNTIF(RAW_Forecast_Data!A:A,A12) -> 49 | I12: =IFERROR(COUNTIFS(RAW_Forecast_Data!A:A,A12,RAW_Forecast_Data!M:M,"Yes")/H12,"") -> 0.40816327
A13: M04 | B13: Claire Pemberton | C13: Mid-Market | D13: =SUMIFS(RAW_Forecast_Data!F:F,RAW_Forecast_Data!A:A,A13,RAW_Forecast_Data!E:E,"<>Q4 2024") -> 2626574.5 | E13: =SUMIFS(RAW_Forecast_Data!G:G,RAW_Forecast_Data!A:A,A13,RAW_Forecast_Data!E:E,"<>Q4 2024") -> 1699234.6 | F13: =IFERROR(1-ABS(D13-E13)/E13,"") -> 0.45426025 | G13: =IF(D13>E13,"Over-Forecaster","Under-Forecaster") -> Over-Forecaster | H13: =COUNTIF(RAW_Forecast_Data!A:A,A13) -> 51 | I13: =IFERROR(COUNTIFS(RAW_Forecast_Data!A:A,A13,RAW_Forecast_Data!M:M,"Yes")/H13,"") -> 0.45098039
A14: M05 | B14: Nathan Griffiths | C14: Mid-Market | D14: =SUMIFS(RAW_Forecast_Data!F:F,RAW_Forecast_Data!A:A,A14,RAW_Forecast_Data!E:E,"<>Q4 2024") -> 2681890.6 | E14: =SUMIFS(RAW_Forecast_Data!G:G,RAW_Forecast_Data!A:A,A14,RAW_Forecast_Data!E:E,"<>Q4 2024") -> 1451053.5 | F14: =IFERROR(1-ABS(D14-E14)/E14,"") -> 0.15176309 | G14: =IF(D14>E14,"Over-Forecaster","Under-Forecaster") -> Over-Forecaster | H14: =COUNTIF(RAW_Forecast_Data!A:A,A14) -> 40 | I14: =IFERROR(COUNTIFS(RAW_Forecast_Data!A:A,A14,RAW_Forecast_Data!M:M,"Yes")/H14,"") -> 0.55
A15: M06 | B15: Yasmin Khalid | C15: Mid-Market | D15: =SUMIFS(RAW_Forecast_Data!F:F,RAW_Forecast_Data!A:A,A15,RAW_Forecast_Data!E:E,"<>Q4 2024") -> 3696704.6 | E15: =SUMIFS(RAW_Forecast_Data!G:G,RAW_Forecast_Data!A:A,A15,RAW_Forecast_Data!E:E,"<>Q4 2024") -> 1792911.8 | F15: =IFERROR(1-ABS(D15-E15)/E15,"") -> -0.061844056 | G15: =IF(D15>E15,"Over-Forecaster","Under-Forecaster") -> Over-Forecaster | H15: =COUNTIF(RAW_Forecast_Data!A:A,A15) -> 47 | I15: =IFERROR(COUNTIFS(RAW_Forecast_Data!A:A,A15,RAW_Forecast_Data!M:M,"Yes")/H15,"") -> 0.31914894
... A17: S01 | B17: Lucy Drummond | C17: SMB | D17: =SUMIFS(RAW_Forecast_Data!F:F,RAW_Forecast_Data!A:A,A17,RAW_Forecast_Data!E:E,"<>Q4 2024") -> 977364.28 | E17: =SUMIFS(RAW_Forecast_Data!G:G,RAW_Forecast_Data!A:A,A17,RAW_Forecast_Data!E:E,"<>Q4 2024") -> 662577.24 | F17: =IFERROR(1-ABS(D17-E17)/E17,"") -> 0.52490514 | G17: =IF(D17>E17,"Over-Forecaster","Under-Forecaster") -> Over-Forecaster | H17: =COUNTIF(RAW_Forecast_Data!A:A,A17) -> 47 | I17: =IFERROR(COUNTIFS(RAW_Forecast_Data!A:A,A17,RAW_Forecast_Data!M:M,"Yes")/H17,"") -> 0.5106383
A18: S02 | B18: Ben Hartley | C18: SMB | D18: =SUMIFS(RAW_Forecast_Data!F:F,RAW_Forecast_Data!A:A,A18,RAW_Forecast_Data!E:E,"<>Q4 2024") -> 1426472 | E18: =SUMIFS(RAW_Forecast_Data!G:G,RAW_Forecast_Data!A:A,A18,RAW_Forecast_Data!E:E,"<>Q4 2024") -> 575113.43 | F18: =IFERROR(1-ABS(D18-E18)/E18,"") -> -0.48033165 | G18: =IF(D18>E18,"Over-Forecaster","Under-Forecaster") -> Over-Forecaster | H18: =COUNTIF(RAW_Forecast_Data!A:A,A18) -> 52 | I18: =IFERROR(COUNTIFS(RAW_Forecast_Data!A:A,A18,RAW_Forecast_Data!M:M,"Yes")/H18,"") -> 0.51923077 | L18: =IFERROR(K16/K17,"")
A19: S03 | B19: Fiona McKenzie | C19: SMB | D19: =SUMIFS(RAW_Forecast_Data!F:F,RAW_Forecast_Data!A:A,A19,RAW_Forecast_Data!E:E,"<>Q4 2024") -> 991403.39 | E19: =SUMIFS(RAW_Forecast_Data!G:G,RAW_Forecast_Data!A:A,A19,RAW_Forecast_Data!E:E,"<>Q4 2024") -> 627810.16 | F19: =IFERROR(1-ABS(D19-E19)/E19,"") -> 0.42085482 | G19: =IF(D19>E19,"Over-Forecaster","Under-Forecaster") -> Over-Forecaster | H19: =COUNTIF(RAW_Forecast_Data!A:A,A19) -> 50 | I19: =IFERROR(COUNTIFS(RAW_Forecast_Data!A:A,A19,RAW_Forecast_Data!M:M,"Yes")/H19,"") -> 0.34
A20: S04 | B20: Callum Reid | C20: SMB | D20: =SUMIFS(RAW_Forecast_Data!F:F,RAW_Forecast_Data!A:A,A20,RAW_Forecast_Data!E:E,"<>Q4 2024") -> 679077.26 | E20: =SUMIFS(RAW_Forecast_Data!G:G,RAW_Forecast_Data!A:A,A20,RAW_Forecast_Data!E:E,"<>Q4 2024") -> 574019.08 | F20: =IFERROR(1-ABS(D20-E20)/E20,"") -> 0.8169779 | G20: =IF(D20>E20,"Over-Forecaster","Under-Forecaster") -> Over-Forecaster | H20: =COUNTIF(RAW_Forecast_Data!A:A,A20) -> 44 | I20: =IFERROR(COUNTIFS(RAW_Forecast_Data!A:A,A20,RAW_Forecast_Data!M:M,"Yes")/H20,"") -> 0.5
A21: S05 | B21: Amara Osei | C21: SMB | D21: =SUMIFS(RAW_Forecast_Data!F:F,RAW_Forecast_Data!A:A,A21,RAW_Forecast_Data!E:E,"<>Q4 2024") -> 1413894.9 | E21: =SUMIFS(RAW_Forecast_Data!G:G,RAW_Forecast_Data!A:A,A21,RAW_Forecast_Data!E:E,"<>Q4 2024") -> 654103.04 | F21: =IFERROR(1-ABS(D21-E21)/E21,"") -> -0.1615782 | G21: =IF(D21>E21,"Over-Forecaster","Under-Forecaster") -> Over-Forecaster | H21: =COUNTIF(RAW_Forecast_Data!A:A,A21) -> 49 | I21: =IFERROR(COUNTIFS(RAW_Forecast_Data!A:A,A21,RAW_Forecast_Data!M:M,"Yes")/H21,"") -> 0.42857143
A22: S06 | B22: Steven Bowman | C22: SMB | D22: =SUMIFS(RAW_Forecast_Data!F:F,RAW_Forecast_Data!A:A,A22,RAW_Forecast_Data!E:E,"<>Q4 2024") -> 1038726.4 | E22: =SUMIFS(RAW_Forecast_Data!G:G,RAW_Forecast_Data!A:A,A22,RAW_Forecast_Data!E:E,"<>Q4 2024") -> 524709.31 | F22: =IFERROR(1-ABS(D22-E22)/E22,"") -> 0.020377435 | G22: =IF(D22>E22,"Over-Forecaster","Under-Forecaster") -> Over-Forecaster | H22: =COUNTIF(RAW_Forecast_Data!A:A,A22) -> 46 | I22: =IFERROR(COUNTIFS(RAW_Forecast_Data!A:A,A22,RAW_Forecast_Data!M:M,"Yes")/H22,"") -> 0.54347826
A23: S07 | B23: Rachel Sutton | C23: SMB | D23: =SUMIFS(RAW_Forecast_Data!F:F,RAW_Forecast_Data!A:A,A23,RAW_Forecast_Data!E:E,"<>Q4 2024") -> 876338.27 | E23: =SUMIFS(RAW_Forecast_Data!G:G,RAW_Forecast_Data!A:A,A23,RAW_Forecast_Data!E:E,"<>Q4 2024") -> 745038.42 | F23: =IFERROR(1-ABS(D23-E23)/E23,"") -> 0.82376768 | G23: =IF(D23>E23,"Over-Forecaster","Under-Forecaster") -> Over-Forecaster | H23: =COUNTIF(RAW_Forecast_Data!A:A,A23) -> 50 | I23: =IFERROR(COUNTIFS(RAW_Forecast_Data!A:A,A23,RAW_Forecast_Data!M:M,"Yes")/H23,"") -> 0.56
A28: SECTION 2 - SEGMENT FORECAST ACCURACY SUMMARY (Q1 to Q3 2024 only)
A29: Segment | B29: Total Forecasted £ | C29: Total Actual Closed £ | D29: Forecast Accuracy % | E29: Average Error %
A30: Enterprise | B30: =SUMIFS(RAW_Forecast_Data!F:F,RAW_Forecast_Data!C:C,A30,RAW_Forecast_Data!E:E,"<>Q4 2024") -> 14380593 | C30: =SUMIFS(RAW_Forecast_Data!G:G,RAW_Forecast_Data!C:C,A30,RAW_Forecast_Data!E:E,"<>Q4 2024") -> 13078342 | D30: =IFERROR(1-ABS(B30-C30)/C30,"") -> 0.90042686 | E30: =IFERROR(ABS(B30-C30)/C30,"") -> 0.099573137
A31: Mid-Market | B31: =SUMIFS(RAW_Forecast_Data!F:F,RAW_Forecast_Data!C:C,A31,RAW_Forecast_Data!E:E,"<>Q4 2024") -> 7907622.5 | C31: =SUMIFS(RAW_Forecast_Data!G:G,RAW_Forecast_Data!C:C,A31,RAW_Forecast_Data!E:E,"<>Q4 2024") -> 3844083.1 | D31: =IFERROR(1-ABS(B31-C31)/C31,"") -> -0.057089374 | E31: =IFERROR(ABS(B31-C31)/C31,"") -> 1.0570894
A32: SMB | B32: =SUMIFS(RAW_Forecast_Data!F:F,RAW_Forecast_Data!C:C,A32,RAW_Forecast_Data!E:E,"<>Q4 2024") -> 3602747.2 | C32: =SUMIFS(RAW_Forecast_Data!G:G,RAW_Forecast_Data!C:C,A32,RAW_Forecast_Data!E:E,"<>Q4 2024") -> 2414286 | D32: =IFERROR(1-ABS(B32-C32)/C32,"") -> 0.50773806 | E32: =IFERROR(ABS(B32-C32)/C32,"") -> 0.49226194
A35: SECTION 3 — QUARTERLY FORECAST ACCURACY SUMMARY
A36: Q4 2024 excluded from accuracy calculation — actual revenue not available as quarter had not closed at time of data export
A37: Quarter | B37: Total Forecasted £ | C37: Total Actual Closed £ | D37: Forecast Accuracy % | E37: Miss Amount £
A38: Q1 2024 | B38: =SUMIFS(RAW_Forecast_Data!F:F,RAW_Forecast_Data!E:E,A38) -> 16813211 | C38: =SUMIFS(RAW_Forecast_Data!G:G,RAW_Forecast_Data!E:E,A38) -> 15230712 | D38: =IFERROR(1-ABS(B38-C38)/C38,"") -> 0.89609814 | E38: =IFERROR(B38-C38,"") -> 1582499.3
A39: Q2 2024 | B39: =SUMIFS(RAW_Forecast_Data!F:F,RAW_Forecast_Data!E:E,A39) -> 24730557 | C39: =SUMIFS(RAW_Forecast_Data!G:G,RAW_Forecast_Data!E:E,A39) -> 16561149 | D39: =IFERROR(1-ABS(B39-C39)/C39,"") -> 0.5067125 | E39: =IFERROR(B39-C39,"") -> 8169407.7
A40: Q3 2024 | B40: =SUMIFS(RAW_Forecast_Data!F:F,RAW_Forecast_Data!E:E,A40) -> 17691460 | C40: =SUMIFS(RAW_Forecast_Data!G:G,RAW_Forecast_Data!E:E,A40) -> 8377362.4 | D40: =IFERROR(1-ABS(B40-C40)/C40,"") -> -0.11181747 | E40: =IFERROR(B40-C40,"") -> 9314097.9
A43: SECTION 4 — PIPELINE SUPPORT ANALYSIS
A44: Total rows flagged | B44: =COUNTIF(Cleaned_Forecast_Data!N:N,"FLAG") -> 76
A45: Total rows in dataset | B45: 1048575
A46: Percentage of rows with no pipeline support | B46: =IFERROR(B44/B45,"") -> 7.2479317e-05
A48: SECTION 5 — WEIGHTED PIPELINE MODEL vs REP FORECAST vs ACTUAL (Q1 to Q3 2024)
A50: Model Forecast = Weighted_Pipeline column (column I) — pipeline adjusted by deal stage probability. Rep Forecast = what the rep manually submitted. Actual = what actually closed.
A51: Rep_ID | B51: Rep_Name | C51: Segment | D51: Rep Forecast £ | E51: Model Forecast £ | F51: Actual Closed £ | G51: Rep Accuracy % | H51: Model Accuracy % | I51: Model Better Than Rep?
A52: E01 | B52: James Whitfield | C52: Enterprise | D52: =SUMIFS(RAW_Forecast_Data!F:F,RAW_Forecast_Data!A:A,A52,RAW_Forecast_Data!E:E,"<>Q4 2024") -> 19225747 | E52: =SUMIFS(RAW_Forecast_Data!I:I,RAW_Forecast_Data!A:A,A52,RAW_Forecast_Data!E:E,"<>Q4 2024") -> 6103274.6 | F52: =SUMIFS(RAW_Forecast_Data!G:G,RAW_Forecast_Data!A:A,A52,RAW_Forecast_Data!E:E,"<>Q4 2024") -> 4793418.1 | G52: =IFERROR(1-ABS(D52-F52)/F52,"") -> -2.0108637 | H52: =IFERROR(1-ABS(E52-F52)/F52,"") -> 0.72673852 | I52: =IF(H52>G52,"Yes — Model Wins","No — Rep Wins") -> Yes — Model Wins
A53: E02 | B53: Sarah Thornton | C53: Enterprise | D53: =SUMIFS(RAW_Forecast_Data!F:F,RAW_Forecast_Data!A:A,A53,RAW_Forecast_Data!E:E,"<>Q4 2024") -> 4452816.2 | E53: =SUMIFS(RAW_Forecast_Data!I:I,RAW_Forecast_Data!A:A,A53,RAW_Forecast_Data!E:E,"<>Q4 2024") -> 4546769.1 | F53: =SUMIFS(RAW_Forecast_Data!G:G,RAW_Forecast_Data!A:A,A53,RAW_Forecast_Data!E:E,"<>Q4 2024") -> 5916007.8 | G53: =IFERROR(1-ABS(D53-F53)/F53,"") -> 0.75267248 | H53: =IFERROR(1-ABS(E53-F53)/F53,"") -> 0.76855361 | I53: =IF(H53>G53,"Yes — Model Wins","No — Rep Wins") -> Yes — Model Wins
A54: E03 | B54: Marcus Bellingham | C54: Enterprise | D54: =SUMIFS(RAW_Forecast_Data!F:F,RAW_Forecast_Data!A:A,A54,RAW_Forecast_Data!E:E,"<>Q4 2024") -> 5471677 | E54: =SUMIFS(RAW_Forecast_Data!I:I,RAW_Forecast_Data!A:A,A54,RAW_Forecast_Data!E:E,"<>Q4 2024") -> 5612114.7 | F54: =SUMIFS(RAW_Forecast_Data!G:G,RAW_Forecast_Data!A:A,A54,RAW_Forecast_Data!E:E,"<>Q4 2024") -> 4481642.6 | G54: =IFERROR(1-ABS(D54-F54)/F54,"") -> 0.77909116 | H54: =IFERROR(1-ABS(E54-F54)/F54,"") -> 0.74775496 | I54: =IF(H54>G54,"Yes — Model Wins","No — Rep Wins") -> No — Rep Wins
A55: E04 | B55: Olivia Hargreaves | C55: Enterprise | D55: =SUMIFS(RAW_Forecast_Data!F:F,RAW_Forecast_Data!A:A,A55,RAW_Forecast_Data!E:E,"<>Q4 2024") -> 5680832.5 | E55: =SUMIFS(RAW_Forecast_Data!I:I,RAW_Forecast_Data!A:A,A55,RAW_Forecast_Data!E:E,"<>Q4 2024") -> 5820065.7 | F55: =SUMIFS(RAW_Forecast_Data!G:G,RAW_Forecast_Data!A:A,A55,RAW_Forecast_Data!E:E,"<>Q4 2024") -> 5029247.9 | G55: =IFERROR(1-ABS(D55-F55)/F55,"") -> 0.87044094 | H55: =IFERROR(1-ABS(E55-F55)/F55,"") -> 0.84275625 | I55: =IF(H55>G55,"Yes — Model Wins","No — Rep Wins") -> No — Rep Wins
A56: E05 | B56: Richard Cavendish | C56: Enterprise | D56: =SUMIFS(RAW_Forecast_Data!F:F,RAW_Forecast_Data!A:A,A56,RAW_Forecast_Data!E:E,"<>Q4 2024") -> 6035497.9 | E56: =SUMIFS(RAW_Forecast_Data!I:I,RAW_Forecast_Data!A:A,A56,RAW_Forecast_Data!E:E,"<>Q4 2024") -> 5423978 | F56: =SUMIFS(RAW_Forecast_Data!G:G,RAW_Forecast_Data!A:A,A56,RAW_Forecast_Data!E:E,"<>Q4 2024") -> 4989297.1 | G56: =IFERROR(1-ABS(D56-F56)/F56,"") -> 0.79031098 | H56: =IFERROR(1-ABS(E56-F56)/F56,"") -> 0.91287733 | I56: =IF(H56>G56,"Yes — Model Wins","No — Rep Wins") -> Yes — Model Wins
A57: E06 | B57: Helena Forsythe | C57: Enterprise | D57: =SUMIFS(RAW_Forecast_Data!F:F,RAW_Forecast_Data!A:A,A57,RAW_Forecast_Data!E:E,"<>Q4 2024") -> 6824711.6 | E57: =SUMIFS(RAW_Forecast_Data!I:I,RAW_Forecast_Data!A:A,A57,RAW_Forecast_Data!E:E,"<>Q4 2024") -> 5053727.3 | F57: =SUMIFS(RAW_Forecast_Data!G:G,RAW_Forecast_Data!A:A,A57,RAW_Forecast_Data!E:E,"<>Q4 2024") -> 4227008.8 | G57: =IFERROR(1-ABS(D57-F57)/F57,"") -> 0.38545127 | H57: =IFERROR(1-ABS(E57-F57)/F57,"") -> 0.80441995 | I57: =IF(H57>G57,"Yes — Model Wins","No — Rep Wins") -> Yes — Model Wins
A58: M01 | B58: Daniel Ashworth | C58: Mid-Market | D58: =SUMIFS(RAW_Forecast_Data!F:F,RAW_Forecast_Data!A:A,A58,RAW_Forecast_Data!E:E,"<>Q4 2024") -> 1767849.6 | E58: =SUMIFS(RAW_Forecast_Data!I:I,RAW_Forecast_Data!A:A,A58,RAW_Forecast_Data!E:E,"<>Q4 2024") -> 1679642.7 | F58: =SUMIFS(RAW_Forecast_Data!G:G,RAW_Forecast_Data!A:A,A58,RAW_Forecast_Data!E:E,"<>Q4 2024") -> 2305549.9 | G58: =IFERROR(1-ABS(D58-F58)/F58,"") -> 0.76678001 | H58: =IFERROR(1-ABS(E58-F58)/F58,"") -> 0.72852152 | I58: =IF(H58>G58,"Yes — Model Wins","No — Rep Wins") -> No — Rep Wins
A59: M02 | B59: Priya Mehta | C59: Mid-Market | D59: =SUMIFS(RAW_Forecast_Data!F:F,RAW_Forecast_Data!A:A,A59,RAW_Forecast_Data!E:E,"<>Q4 2024") -> 2867670.5 | E59: =SUMIFS(RAW_Forecast_Data!I:I,RAW_Forecast_Data!A:A,A59,RAW_Forecast_Data!E:E,"<>Q4 2024") -> 2414614 | F59: =SUMIFS(RAW_Forecast_Data!G:G,RAW_Forecast_Data!A:A,A59,RAW_Forecast_Data!E:E,"<>Q4 2024") -> 1945103.2 | G59: =IFERROR(1-ABS(D59-F59)/F59,"") -> 0.52569755 | H59: =IFERROR(1-ABS(E59-F59)/F59,"") -> 0.75861911 | I59: =IF(H59>G59,"Yes — Model Wins","No — Rep Wins") -> Yes — Model Wins
A60: M03 | B60: Tom Baxter | C60: Mid-Market | D60: =SUMIFS(RAW_Forecast_Data!F:F,RAW_Forecast_Data!A:A,A60,RAW_Forecast_Data!E:E,"<>Q4 2024") -> 4555593.9 | E60: =SUMIFS(RAW_Forecast_Data!I:I,RAW_Forecast_Data!A:A,A60,RAW_Forecast_Data!E:E,"<>Q4 2024") -> 2734400.6 | F60: =SUMIFS(RAW_Forecast_Data!G:G,RAW_Forecast_Data!A:A,A60,RAW_Forecast_Data!E:E,"<>Q4 2024") -> 1377349.9 | G60: =IFERROR(1-ABS(D60-F60)/F60,"") -> -1.3075067 | H60: =IFERROR(1-ABS(E60-F60)/F60,"") -> 0.01473786 | I60: =IF(H60>G60,"Yes — Model Wins","No — Rep Wins") -> Yes — Model Wins
A61: M04 | B61: Claire Pemberton | C61: Mid-Market | D61: =SUMIFS(RAW_Forecast_Data!F:F,RAW_Forecast_Data!A:A,A61,RAW_Forecast_Data!E:E,"<>Q4 2024") -> 2626574.5 | E61: =SUMIFS(RAW_Forecast_Data!I:I,RAW_Forecast_Data!A:A,A61,RAW_Forecast_Data!E:E,"<>Q4 2024") -> 2144917.5 | F61: =SUMIFS(RAW_Forecast_Data!G:G,RAW_Forecast_Data!A:A,A61,RAW_Forecast_Data!E:E,"<>Q4 2024") -> 1699234.6 | G61: =IFERROR(1-ABS(D61-F61)/F61,"") -> 0.45426025 | H61: =IFERROR(1-ABS(E61-F61)/F61,"") -> 0.7377155 | I61: =IF(H61>G61,"Yes — Model Wins","No — Rep Wins") -> Yes — Model Wins
A62: M05 | B62: Nathan Griffiths | C62: Mid-Market | D62: =SUMIFS(RAW_Forecast_Data!F:F,RAW_Forecast_Data!A:A,A62,RAW_Forecast_Data!E:E,"<>Q4 2024") -> 2681890.6 | E62: =SUMIFS(RAW_Forecast_Data!I:I,RAW_Forecast_Data!A:A,A62,RAW_Forecast_Data!E:E,"<>Q4 2024") -> 1858592.3 | F62: =SUMIFS(RAW_Forecast_Data!G:G,RAW_Forecast_Data!A:A,A62,RAW_Forecast_Data!E:E,"<>Q4 2024") -> 1451053.5 | G62: =IFERROR(1-ABS(D62-F62)/F62,"") -> 0.15176309 | H62: =IFERROR(1-ABS(E62-F62)/F62,"") -> 0.71914285 | I62: =IF(H62>G62,"Yes — Model Wins","No — Rep Wins") -> Yes — Model Wins
A63: M06 | B63: Yasmin Khalid | C63: Mid-Market | D63: =SUMIFS(RAW_Forecast_Data!F:F,RAW_Forecast_Data!A:A,A63,RAW_Forecast_Data!E:E,"<>Q4 2024") -> 3696704.6 | E63: =SUMIFS(RAW_Forecast_Data!I:I,RAW_Forecast_Data!A:A,A63,RAW_Forecast_Data!E:E,"<>Q4 2024") -> 2187905.4 | F63: =SUMIFS(RAW_Forecast_Data!G:G,RAW_Forecast_Data!A:A,A63,RAW_Forecast_Data!E:E,"<>Q4 2024") -> 1792911.8 | G63: =IFERROR(1-ABS(D63-F63)/F63,"") -> -0.061844056 | H63: =IFERROR(1-ABS(E63-F63)/F63,"") -> 0.77969159 | I63: =IF(H63>G63,"Yes — Model Wins","No — Rep Wins") -> Yes — Model Wins
... A71: S07 | B71: Rachel Sutton | C71: SMB | D71: =SUMIFS(RAW_Forecast_Data!F:F,RAW_Forecast_Data!A:A,A71,RAW_Forecast_Data!E:E,"<>Q4 2024") -> 876338.27 | E71: =SUMIFS(RAW_Forecast_Data!I:I,RAW_Forecast_Data!A:A,A71,RAW_Forecast_Data!E:E,"<>Q4 2024") -> 833838.5 | F71: =SUMIFS(RAW_Forecast_Data!G:G,RAW_Forecast_Data!A:A,A71,RAW_Forecast_Data!E:E,"<>Q4 2024") -> 745038.42 | G71: =IFERROR(1-ABS(D71-F71)/F71,"") -> 0.82376768 | H71: =IFERROR(1-ABS(E71-F71)/F71,"") -> 0.88081141 | I71: =IF(H71>G71,"Yes — Model Wins","No — Rep Wins") -> Yes — Model Wins

Sheet Data_Dictionary
A1: Column_Name | B1: Description | C1: Data_Type | D1: Expected_Format | E1: Example_Value | F1: Notes
A2: Rep_ID | B2: Unique identifier for each sales representative | C2: Text | D2: Letter + 2 digits e.g. E01, M03, S07 | E2: E01 | F2: E = Enterprise, M = Mid-Market, S = SMB
A3: Rep_Name | B3: Full name of the sales representative | C3: Text | D3: First name and surname | E3: James Whitfield | F3: Should be consistent across all rows for the same rep
A4: Segment | B4: The market segment the rep sells into | C4: Text | D4: One of three values: Enterprise, Mid-Market, SMB | E4: Enterprise | F4: Inconsistent formatting found in raw data — needs standardising
A5: Week_Ending_Date | B5: The Friday that marks the end of the working week the forecast covers | C5: Date | D5: DD/MM/YYYY | E5: 05/01/2024 | F5: Multiple date formats found in raw data — needs standardising
A6: Quarter | B6: The financial quarter the week falls within | C6: Text | D6: Q1 2024 / Q2 2024 / Q3 2024 / Q4 2024 | E6: Q1 2024 | F6: Inconsistent labels found in raw data — needs standardising
A7: Forecasted_Revenue | B7: The revenue the rep predicted they would close in that week | C7: Number | D7: Numeric value in GBP — no symbols or commas | E7: 125000 | F7: Some entries found as text strings e.g. £125,000 — needs cleaning
A8: Actual_Revenue_Closed | B8: The revenue the rep actually closed by end of that week | C8: Number | D8: Numeric value in GBP — no symbols or commas | E8: 118000 | F8: Blank for all Q4 2024 rows as the quarter had not yet closed at time of data export
A9: Pipeline_Value | B9: Total value of all active deals the rep currently has in progress | C9: Number | D9: Numeric value in GBP — no symbols or commas | E9: 450000 | F9: Should always be higher than Forecasted_Revenue — flag where it is not
A10: Weighted_Pipeline | B10: Pipeline value adjusted by probability of closing based on deal stage | C10: Number | D10: Numeric value in GBP — no symbols or commas | E10: 157500 | F10: Calculated field — should always be lower than Pipeline_Value
A11: Stage_Distribution | B11: Breakdown of where the rep's deals sit across the four pipeline stages | C11: Text | D11: Qualify:XX%, Propose:XX%, Negotiate:XX%, Close:XX% | E11: Qualify:20%,Propose:35%,Negotiate:30%,Close:15% | F11: Percentages should sum to 100%
A12: Deal_Count_Forecasted | B12: Number of individual deals the rep predicted they would close that week | C12: Number | D12: Whole number — no decimals | E12: 3 | F12: Should be reviewed alongside Forecasted_Revenue — large revenue on 1 deal is high risk
... A15: Notes | B15: Free text comment added by the rep or their manager about that week's forecast | C15: Text | D15: Free text — optional field | E15: Two deals slipped to next week | F15: Many blanks, N/A, n/a, and dashes present — treat all as blank during cleaning

Sheet Messy_Data_Log
A1: Column_Name | B1: Issue_Found | C1: Rows_Affected | D1: Example | E1: Impact | F1: Cleaning_Action_Planned
A2: Segment | B2: Inconsistent values, same segment entered in multiple different ways | C2: Multiple rows affected across all reps | D2: Enterprise, ENT, enterprise, Ent, ENTERPRISE all found in same column | E2: Segment-level analysis and filtering will break if not standardised | F2: Standardise all values to Enterprise, Mid-Market, or SMB only
A3: Week_Ending_Date | B3: Inconsistent date format - same date type entered in multiple formats | C3: Multiple rows affected across all reps | D3: 05/01/2024, 05-01-2024, 05 Jan 2024, 2024-01-05 all found in same column. | E3: Date-based calculations, sorting, and time series analysis will break if not standardised | F3: Standardise all dates to DD/MM/YYYY format
A4: Quarter | B4: Inconsistent labels, same quarter expressed in multiple different ways | C4: Multiple rows affected across all reps | D4: Q1 2024, Q1-2024, Q1, q1 2024, Jan-Mar 2024 all found in same column | E4: Quarter-level analysis and filtering will produce incorrect results if not standardised | F4: Standardise all values to Q1 2024, Q2 2024, Q3 2024, Q4 2024 format only
A5: Forecasted_Revenue | B5: Mixed data types, some values entered as text strings instead of numbers | C5: Approximately 47 rows affected | D5: £125,000 and GBP 45,000 and 45k found instead of plain numeric values | E5: Any formula or calculation using this column will return an error or be ignored where values are text | F5: Strip all symbols and text, convert all values to plain numbers
A6: Actual_Revenue_Closed | B6: Blank values, entire quarter missing actual revenue figures | C6: Approximately 241 rows affected ,all Q4 2024 rows | D6: Cells are blank where quarter has not yet closed at time of data export | E6: Forecast accuracy calculations will fail or be skewed if blanks are not handled correctly | F6: Exclude all Q4 2024 rows from any forecast accuracy calculations, do not delete them
A7: Forecast_Submitted_On_Time | B7: Inconsistent values - same Yes/No answer entered in multiple different ways | C7: Multiple rows affected across all reps | D7: Yes, yes, YES, Y, y, No, no, NO, N, Late, LATE all found in same column | E7: Submission compliance reporting will be inaccurate if values are not standardised | F7: Standardise all positive values to Yes and all negative values to No
A8: Notes | B8: Inconsistent blank values — empty notes recorded in multiple different ways | C8: Multiple rows affected across all reps | D8: Multiple rows affected across all reps | E8: Inconsistent nulls will cause issues if Notes column is used for any filtering or categorisation | F8: Standardise all variations of blank to a single blank empty cell
A9: Pipeline_Value | B9: Pipeline value lower than Forecasted_Revenue — no pipeline support for the forecast number | C9: Approximately 58 rows affected | D9: Pipeline_Value found to be less than 30% of Forecasted_Revenue in same row | E9: Indicates rep has submitted a forecast with no deals to support it — a key accuracy risk | F9: Flag these rows with a marker column during cleaning — do not delete them
A10: Actual_Revenue_Closed / Deal_Count_Closed | B10: Missing submissions — some reps have no row at all for certain weeks | C10: Approximately 50 to 60 rows missing across Callum Reid and Nathan Griffiths primarily | D10: No row exists for these reps for certain weeks — not a blank value but a missing record entirely | E10: Missing submissions mean these reps have gaps in their forecast accuracy history which will skew their performance metrics | F10: Note the missing weeks in analysis — do not fabricate data to fill gaps
